Workbook

Sheet Summary Dashboard
A1: ADVERTISING CAMPAIGN PERFORMANCE DASHBOARD
A3: KEY METRICS SUMMARY | H3: TOP AUDIENCE SEGMENTS BY IMPRESSIONS
A4: Total Impressions | B4: =SUM(PBL_DA_CAPSTONE_DATA!K:K) -> 85705314 | H4: Audience Segment | I4: Impressions | J4: Clicks | K4: Conversions | L4: Gross Cost
A5: Total Clicks | B5: =SUM(PBL_DA_CAPSTONE_DATA!L:L) -> 233099 | H5: Automotive | I5: =SUMIF(PBL_DA_CAPSTONE_DATA!A:A,"Automotive",PBL_DA_CAPSTONE_DATA!K:K) -> 12709966 | J5: =SUMIF(PBL_DA_CAPSTONE_DATA!A:A,"Automotive",PBL_DA_CAPSTONE_DATA!L:L) -> 37608 | K5: =SUMIF(PBL_DA_CAPSTONE_DATA!A:A,"Automotive",PBL_DA_CAPSTONE_DATA!U:U) -> 0 | L5: =SUMIF(PBL_DA_CAPSTONE_DATA!A:A,"Automotive",PBL_DA_CAPSTONE_DATA!V:V) -> 0
A6: Total Viewable Impressions | B6: =SUM(PBL_DA_CAPSTONE_DATA!M:M) -> 41896691 | H6: Beauty and Fitness | I6: =SUMIF(PBL_DA_CAPSTONE_DATA!A:A,"Beauty and Fitness",PBL_DA_CAPSTONE_DATA!K:K) -> 4609241 | J6: =SUMIF(PBL_DA_CAPSTONE_DATA!A:A,"Beauty and Fitness",PBL_DA_CAPSTONE_DATA!L:L) -> 14384 | K6: =SUMIF(PBL_DA_CAPSTONE_DATA!A:A,"Beauty and Fitness",PBL_DA_CAPSTONE_DATA!U:U) -> 0 | L6: =SUMIF(PBL_DA_CAPSTONE_DATA!A:A,"Beauty and Fitness",PBL_DA_CAPSTONE_DATA!V:V) -> 0
A7: Total Conversions | B7: =SUM(PBL_DA_CAPSTONE_DATA!U:U) -> 0 | H7: B2B | I7: =SUMIF(PBL_DA_CAPSTONE_DATA!A:A,"B2B",PBL_DA_CAPSTONE_DATA!K:K) -> 2617549 | J7: =SUMIF(PBL_DA_CAPSTONE_DATA!A:A,"B2B",PBL_DA_CAPSTONE_DATA!L:L) -> 7372 | K7: =SUMIF(PBL_DA_CAPSTONE_DATA!A:A,"B2B",PBL_DA_CAPSTONE_DATA!U:U) -> 0 | L7: =SUMIF(PBL_DA_CAPSTONE_DATA!A:A,"B2B",PBL_DA_CAPSTONE_DATA!V:V) -> 0
A8: Total Gross Cost | B8: =SUM(PBL_DA_CAPSTONE_DATA!V:V) -> 0 | H8: Brand Propensities | I8: =SUMIF(PBL_DA_CAPSTONE_DATA!A:A,"Brand Propensities",PBL_DA_CAPSTONE_DATA!K:K) -> 4191580 | J8: =SUMIF(PBL_DA_CAPSTONE_DATA!A:A,"Brand Propensities",PBL_DA_CAPSTONE_DATA!L:L) -> 11567 | K8: =SUMIF(PBL_DA_CAPSTONE_DATA!A:A,"Brand Propensities",PBL_DA_CAPSTONE_DATA!U:U) -> 0 | L8: =SUMIF(PBL_DA_CAPSTONE_DATA!A:A,"Brand Propensities",PBL_DA_CAPSTONE_DATA!V:V) -> 0
A9: Overall CTR (Click-Through Rate) | B9: =IF(B4>0,B5/B4,0) -> 0.002719773 | H9: Arts and Entertainment | I9: =SUMIF(PBL_DA_CAPSTONE_DATA!A:A,"Arts and Entertainment",PBL_DA_CAPSTONE_DATA!K:K) -> 1279283 | J9: =SUMIF(PBL_DA_CAPSTONE_DATA!A:A,"Arts and Entertainment",PBL_DA_CAPSTONE_DATA!L:L) -> 2947 | K9: =SUMIF(PBL_DA_CAPSTONE_DATA!A:A,"Arts and Entertainment",PBL_DA_CAPSTONE_DATA!U:U) -> 0 | L9: =SUMIF(PBL_DA_CAPSTONE_DATA!A:A,"Arts and Entertainment",PBL_DA_CAPSTONE_DATA!V:V) -> 0
H10: Finance | I10: =SUMIF(PBL_DA_CAPSTONE_DATA!A:A,"Finance",PBL_DA_CAPSTONE_DATA!K:K) -> 13200810 | J10: =SUMIF(PBL_DA_CAPSTONE_DATA!A:A,"Finance",PBL_DA_CAPSTONE_DATA!L:L) -> 25675 | K10: =SUMIF(PBL_DA_CAPSTONE_DATA!A:A,"Finance",PBL_DA_CAPSTONE_DATA!U:U) -> 0 | L10: =SUMIF(PBL_DA_CAPSTONE_DATA!A:A,"Finance",PBL_DA_CAPSTONE_DATA!V:V) -> 0
A11: PERFORMANCE BY STATE | H11: Demographics | I11: =SUMIF(PBL_DA_CAPSTONE_DATA!A:A,"Demographics",PBL_DA_CAPSTONE_DATA!K:K) -> 886174 | J11: =SUMIF(PBL_DA_CAPSTONE_DATA!A:A,"Demographics",PBL_DA_CAPSTONE_DATA!L:L) -> 1981 | K11: =SUMIF(PBL_DA_CAPSTONE_DATA!A:A,"Demographics",PBL_DA_CAPSTONE_DATA!U:U) -> 0 | L11: =SUMIF(PBL_DA_CAPSTONE_DATA!A:A,"Demographics",PBL_DA_CAPSTONE_DATA!V:V) -> 0
A12: State | B12: Impressions | C12: Clicks | D12: Conversions | E12: Gross Cost | F12: CTR | H12: Food | I12: =SUMIF(PBL_DA_CAPSTONE_DATA!A:A,"Food",PBL_DA_CAPSTONE_DATA!K:K) -> 1981212 | J12: =SUMIF(PBL_DA_CAPSTONE_DATA!A:A,"Food",PBL_DA_CAPSTONE_DATA!L:L) -> 5498 | K12: =SUMIF(PBL_DA_CAPSTONE_DATA!A:A,"Food",PBL_DA_CAPSTONE_DATA!U:U) -> 0 | L12: =SUMIF(PBL_DA_CAPSTONE_DATA!A:A,"Food",PBL_DA_CAPSTONE_DATA!V:V) -> 0
A13: California | B13: =SUMIF(PBL_DA_CAPSTONE_DATA!G:G,"*California*",PBL_DA_CAPSTONE_DATA!K:K) -> 20155086 | C13: =SUMIF(PBL_DA_CAPSTONE_DATA!G:G,"*California*",PBL_DA_CAPSTONE_DATA!L:L) -> 55756 | D13: =SUMIF(PBL_DA_CAPSTONE_DATA!G:G,"*California*",PBL_DA_CAPSTONE_DATA!U:U) -> 0 | E13: =SUMIF(PBL_DA_CAPSTONE_DATA!G:G,"*California*",PBL_DA_CAPSTONE_DATA!V:V) -> 0 | F13: =IF(B13>0,C13/B13,0) -> 0.0027663489 | H13: Home and Garden | I13: =SUMIF(PBL_DA_CAPSTONE_DATA!A:A,"Home and Garden",PBL_DA_CAPSTONE_DATA!K:K) -> 281692 | J13: =SUMIF(PBL_DA_CAPSTONE_DATA!A:A,"Home and Garden",PBL_DA_CAPSTONE_DATA!L:L) -> 1059 | K13: =SUMIF(PBL_DA_CAPSTONE_DATA!A:A,"Home and Garden",PBL_DA_CAPSTONE_DATA!U:U) -> 0 | L13: =SUMIF(PBL_DA_CAPSTONE_DATA!A:A,"Home and Garden",PBL_DA_CAPSTONE_DATA!V:V) -> 0
A14: Florida | B14: =SUMIF(PBL_DA_CAPSTONE_DATA!G:G,"*Florida*",PBL_DA_CAPSTONE_DATA!K:K) -> 12361492 | C14: =SUMIF(PBL_DA_CAPSTONE_DATA!G:G,"*Florida*",PBL_DA_CAPSTONE_DATA!L:L) -> 36764 | D14: =SUMIF(PBL_DA_CAPSTONE_DATA!G:G,"*Florida*",PBL_DA_CAPSTONE_DATA!U:U) -> 0 | E14: =SUMIF(PBL_DA_CAPSTONE_DATA!G:G,"*Florida*",PBL_DA_CAPSTONE_DATA!V:V) -> 0 | F14: =IF(B14>0,C14/B14,0) -> 0.0029740747 | H14: Media and Entertainment | I14: =SUMIF(PBL_DA_CAPSTONE_DATA!A:A,"Media and Entertainment",PBL_DA_CAPSTONE_DATA!K:K) -> 2705224 | J14: =SUMIF(PBL_DA_CAPSTONE_DATA!A:A,"Media and Entertainment",PBL_DA_CAPSTONE_DATA!L:L) -> 8163 | K14: =SUMIF(PBL_DA_CAPSTONE_DATA!A:A,"Media and Entertainment",PBL_DA_CAPSTONE_DATA!U:U) -> 0 | L14: =SUMIF(PBL_DA_CAPSTONE_DATA!A:A,"Media and Entertainment",PBL_DA_CAPSTONE_DATA!V:V) -> 0
A15: Illinois | B15: =SUMIF(PBL_DA_CAPSTONE_DATA!G:G,"*Illinois*",PBL_DA_CAPSTONE_DATA!K:K) -> 27857546 | C15: =SUMIF(PBL_DA_CAPSTONE_DATA!G:G,"*Illinois*",PBL_DA_CAPSTONE_DATA!L:L) -> 69176 | D15: =SUMIF(PBL_DA_CAPSTONE_DATA!G:G,"*Illinois*",PBL_DA_CAPSTONE_DATA!U:U) -> 0 | E15: =SUMIF(PBL_DA_CAPSTONE_DATA!G:G,"*Illinois*",PBL_DA_CAPSTONE_DATA!V:V) -> 0 | F15: =IF(B15>0,C15/B15,0) -> 0.0024832051
A16: New York | B16: =SUMIF(PBL_DA_CAPSTONE_DATA!G:G,"*New York*",PBL_DA_CAPSTONE_DATA!K:K) -> 12389658 | C16: =SUMIF(PBL_DA_CAPSTONE_DATA!G:G,"*New York*",PBL_DA_CAPSTONE_DATA!L:L) -> 35141 | D16: =SUMIF(PBL_DA_CAPSTONE_DATA!G:G,"*New York*",PBL_DA_CAPSTONE_DATA!U:U) -> 0 | E16: =SUMIF(PBL_DA_CAPSTONE_DATA!G:G,"*New York*",PBL_DA_CAPSTONE_DATA!V:V) -> 0 | F16: =IF(B16>0,C16/B16,0) -> 0.0028363172
A17: Tennessee | B17: =SUMIF(PBL_DA_CAPSTONE_DATA!G:G,"*Tennessee*",PBL_DA_CAPSTONE_DATA!K:K) -> 6235010 | C17: =SUMIF(PBL_DA_CAPSTONE_DATA!G:G,"*Tennessee*",PBL_DA_CAPSTONE_DATA!L:L) -> 17186 | D17: =SUMIF(PBL_DA_CAPSTONE_DATA!G:G,"*Tennessee*",PBL_DA_CAPSTONE_DATA!U:U) -> 0 | E17: =SUMIF(PBL_DA_CAPSTONE_DATA!G:G,"*Tennessee*",PBL_DA_CAPSTONE_DATA!V:V) -> 0 | F17: =IF(B17>0,C17/B17,0) -> 0.0027563709 | H17: TOP AD EXCHANGES
A18: Michigan | B18: =SUMIF(PBL_DA_CAPSTONE_DATA!G:G,"*Michigan*",PBL_DA_CAPSTONE_DATA!K:K) -> 2424081 | C18: =SUMIF(PBL_DA_CAPSTONE_DATA!G:G,"*Michigan*",PBL_DA_CAPSTONE_DATA!L:L) -> 7456 | D18: =SUMIF(PBL_DA_CAPSTONE_DATA!G:G,"*Michigan*",PBL_DA_CAPSTONE_DATA!U:U) -> 0 | E18: =SUMIF(PBL_DA_CAPSTONE_DATA!G:G,"*Michigan*",PBL_DA_CAPSTONE_DATA!V:V) -> 0 | F18: =IF(B18>0,C18/B18,0) -> 0.0030758048 | H18: Exchange | I18: Impressions | J18: Clicks | K18: Gross Cost
A19: Indiana | B19: =SUMIF(PBL_DA_CAPSTONE_DATA!G:G,"*Indiana*",PBL_DA_CAPSTONE_DATA!K:K) -> 1901207 | C19: =SUMIF(PBL_DA_CAPSTONE_DATA!G:G,"*Indiana*",PBL_DA_CAPSTONE_DATA!L:L) -> 4811 | D19: =SUMIF(PBL_DA_CAPSTONE_DATA!G:G,"*Indiana*",PBL_DA_CAPSTONE_DATA!U:U) -> 0 | E19: =SUMIF(PBL_DA_CAPSTONE_DATA!G:G,"*Indiana*",PBL_DA_CAPSTONE_DATA!V:V) -> 0 | F19: =IF(B19>0,C19/B19,0) -> 0.0025304977 | H19: Google Ad Manager | I19: =SUMIF(PBL_DA_CAPSTONE_DATA!I:I,"Google Ad Manager",PBL_DA_CAPSTONE_DATA!K:K) -> 34342307 | J19: =SUMIF(PBL_DA_CAPSTONE_DATA!I:I,"Google Ad Manager",PBL_DA_CAPSTONE_DATA!L:L) -> 97488 | K19: =SUMIF(PBL_DA_CAPSTONE_DATA!I:I,"Google Ad Manager",PBL_DA_CAPSTONE_DATA!V:V) -> 0
A20: Georgia | B20: =SUMIF(PBL_DA_CAPSTONE_DATA!G:G,"*Georgia*",PBL_DA_CAPSTONE_DATA!K:K) -> 724339 | C20: =SUMIF(PBL_DA_CAPSTONE_DATA!G:G,"*Georgia*",PBL_DA_CAPSTONE_DATA!L:L) -> 2045 | D20: =SUMIF(PBL_DA_CAPSTONE_DATA!G:G,"*Georgia*",PBL_DA_CAPSTONE_DATA!U:U) -> 0 | E20: =SUMIF(PBL_DA_CAPSTONE_DATA!G:G,"*Georgia*",PBL_DA_CAPSTONE_DATA!V:V) -> 0 | F20: =IF(B20>0,C20/B20,0) -> 0.0028232637 | H20: BidSwitch | I20: =SUMIF(PBL_DA_CAPSTONE_DATA!I:I,"BidSwitch",PBL_DA_CAPSTONE_DATA!K:K) -> 8708607 | J20: =SUMIF(PBL_DA_CAPSTONE_DATA!I:I,"BidSwitch",PBL_DA_CAPSTONE_DATA!L:L) -> 23187 | K20: =SUMIF(PBL_DA_CAPSTONE_DATA!I:I,"BidSwitch",PBL_DA_CAPSTONE_DATA!V:V) -> 0
A21: Alabama | B21: =SUMIF(PBL_DA_CAPSTONE_DATA!G:G,"*Alabama*",PBL_DA_CAPSTONE_DATA!K:K) -> 183819 | C21: =SUMIF(PBL_DA_CAPSTONE_DATA!G:G,"*Alabama*",PBL_DA_CAPSTONE_DATA!L:L) -> 693 | D21: =SUMIF(PBL_DA_CAPSTONE_DATA!G:G,"*Alabama*",PBL_DA_CAPSTONE_DATA!U:U) -> 0 | E21: =SUMIF(PBL_DA_CAPSTONE_DATA!G:G,"*Alabama*",PBL_DA_CAPSTONE_DATA!V:V) -> 0 | F21: =IF(B21>0,C21/B21,0) -> 0.0037700129 | H21: PubMatic | I21: =SUMIF(PBL_DA_CAPSTONE_DATA!I:I,"PubMatic",PBL_DA_CAPSTONE_DATA!K:K) -> 13445406 | J21: =SUMIF(PBL_DA_CAPSTONE_DATA!I:I,"PubMatic",PBL_DA_CAPSTONE_DATA!L:L) -> 28722 | K21: =SUMIF(PBL_DA_CAPSTONE_DATA!I:I,"PubMatic",PBL_DA_CAPSTONE_DATA!V:V) -> 0
A22: Ohio | B22: =SUMIF(PBL_DA_CAPSTONE_DATA!G:G,"*Ohio*",PBL_DA_CAPSTONE_DATA!K:K) -> 256526 | C22: =SUMIF(PBL_DA_CAPSTONE_DATA!G:G,"*Ohio*",PBL_DA_CAPSTONE_DATA!L:L) -> 707 | D22: =SUMIF(PBL_DA_CAPSTONE_DATA!G:G,"*Ohio*",PBL_DA_CAPSTONE_DATA!U:U) -> 0 | E22: =SUMIF(PBL_DA_CAPSTONE_DATA!G:G,"*Ohio*",PBL_DA_CAPSTONE_DATA!V:V) -> 0 | F22: =IF(B22>0,C22/B22,0) -> 0.0027560559 | H22: Magnite DV+ | I22: =SUMIF(PBL_DA_CAPSTONE_DATA!I:I,"Magnite DV+",PBL_DA_CAPSTONE_DATA!K:K) -> 8362480 | J22: =SUMIF(PBL_DA_CAPSTONE_DATA!I:I,"Magnite DV+",PBL_DA_CAPSTONE_DATA!L:L) -> 24491 | K22: =SUMIF(PBL_DA_CAPSTONE_DATA!I:I,"Magnite DV+",PBL_DA_CAPSTONE_DATA!V:V) -> 0
H23: Index Exchange | I23: =SUMIF(PBL_DA_CAPSTONE_DATA!I:I,"Index Exchange",PBL_DA_CAPSTONE_DATA!K:K) -> 3682064 | J23: =SUMIF(PBL_DA_CAPSTONE_DATA!I:I,"Index Exchange",PBL_DA_CAPSTONE_DATA!L:L) -> 10517 | K23: =SUMIF(PBL_DA_CAPSTONE_DATA!I:I,"Index Exchange",PBL_DA_CAPSTONE_DATA!V:V) -> 0
H24: OpenX | I24: =SUMIF(PBL_DA_CAPSTONE_DATA!I:I,"OpenX",PBL_DA_CAPSTONE_DATA!K:K) -> 4462460 | J24: =SUMIF(PBL_DA_CAPSTONE_DATA!I:I,"OpenX",PBL_DA_CAPSTONE_DATA!L:L) -> 13209 | K24: =SUMIF(PBL_DA_CAPSTONE_DATA!I:I,"OpenX",PBL_DA_CAPSTONE_DATA!V:V) -> 0
A25: PERFORMANCE BY DEVICE
A26: Device Make | B26: Impressions | C26: Clicks | D26: Gross Cost | E26: CTR
A27: Smartphone | B27: =SUMIF(PBL_DA_CAPSTONE_DATA!J:J,"Smartphone",PBL_DA_CAPSTONE_DATA!K:K) -> 78213490 | C27: =SUMIF(PBL_DA_CAPSTONE_DATA!J:J,"Smartphone",PBL_DA_CAPSTONE_DATA!L:L) -> 210740 | D27: =SUMIF(PBL_DA_CAPSTONE_DATA!J:J,"Smartphone",PBL_DA_CAPSTONE_DATA!V:V) -> 0 | E27: =IF(B27>0,C27/B27,0) -> 0.0026944201
A28: Windows PC | B28: =SUMIF(PBL_DA_CAPSTONE_DATA!J:J,"Windows PC",PBL_DA_CAPSTONE_DATA!K:K) -> 4686681 | C28: =SUMIF(PBL_DA_CAPSTONE_DATA!J:J,"Windows PC",PBL_DA_CAPSTONE_DATA!L:L) -> 13372 | D28: =SUMIF(PBL_DA_CAPSTONE_DATA!J:J,"Windows PC",PBL_DA_CAPSTONE_DATA!V:V) -> 0 | E28: =IF(B28>0,C28/B28,0) -> 0.0028531918
A29: Apple PC | B29: =SUMIF(PBL_DA_CAPSTONE_DATA!J:J,"Apple PC",PBL_DA_CAPSTONE_DATA!K:K) -> 2805143 | C29: =SUMIF(PBL_DA_CAPSTONE_DATA!J:J,"Apple PC",PBL_DA_CAPSTONE_DATA!L:L) -> 8987 | D29: =SUMIF(PBL_DA_CAPSTONE_DATA!J:J,"Apple PC",PBL_DA_CAPSTONE_DATA!V:V) -> 0 | E29: =IF(B29>0,C29/B29,0) -> 0.0032037582
A74: PERFORMANCE BY CREATIVE SIZE | H74: PERFORMANCE BY CREATIVE MESSAGING
A75: Creative Size | B75: Impressions | C75: Clicks | D75: Conversions | E75: CTR | H75: Creative Messaging | I75: Impressions | J75: Clicks | K75: Conversions | L75: CTR
A76: 320x50 | B76: =SUMIF(PBL_DA_CAPSTONE_DATA!D:D,"320x50",PBL_DA_CAPSTONE_DATA!K:K) -> 40014637 | C76: =SUMIF(PBL_DA_CAPSTONE_DATA!D:D,"320x50",PBL_DA_CAPSTONE_DATA!L:L) -> 102729 | D76: =SUMIF(PBL_DA_CAPSTONE_DATA!D:D,"320x50",PBL_DA_CAPSTONE_DATA!U:U) -> 0 | E76: =IF(B76>0,C76/B76,0) -> 0.0025672856 | H76: Subscribe Today - 10% Discount | I76: =SUMIF(PBL_DA_CAPSTONE_DATA!E:E,"Subscribe Today - 10% Discount",PBL_DA_CAPSTONE_DATA!K:K) -> 22412582 | J76: =SUMIF(PBL_DA_CAPSTONE_DATA!E:E,"Subscribe Today - 10% Discount",PBL_DA_CAPSTONE_DATA!L:L) -> 65302 | K76: =SUMIF(PBL_DA_CAPSTONE_DATA!E:E,"Subscribe Today - 10% Discount",PBL_DA_CAPSTONE_DATA!U:U) -> 0 | L76: =IF(I76>0,J76/I76,0) -> 0.0029136313
A77: 300x250 | B77: =SUMIF(PBL_DA_CAPSTONE_DATA!D:D,"300x250",PBL_DA_CAPSTONE_DATA!K:K) -> 40755215 | C77: =SUMIF(PBL_DA_CAPSTONE_DATA!D:D,"300x250",PBL_DA_CAPSTONE_DATA!L:L) -> 115476 | D77: =SUMIF(PBL_DA_CAPSTONE_DATA!D:D,"300x250",PBL_DA_CAPSTONE_DATA!U:U) -> 0 | E77: =IF(B77>0,C77/B77,0) -> 0.0028334043 | H77: Sign up Today - 10% Off | I77: =SUMIF(PBL_DA_CAPSTONE_DATA!E:E,"Sign up Today - 10% Off",PBL_DA_CAPSTONE_DATA!K:K) -> 21106602 | J77: =SUMIF(PBL_DA_CAPSTONE_DATA!E:E,"Sign up Today - 10% Off",PBL_DA_CAPSTONE_DATA!L:L) -> 60421 | K77: =SUMIF(PBL_DA_CAPSTONE_DATA!E:E,"Sign up Today - 10% Off",PBL_DA_CAPSTONE_DATA!U:U) -> 0 | L77: =IF(I77>0,J77/I77,0) -> 0.0028626588
A78: 300x50 | B78: =SUMIF(PBL_DA_CAPSTONE_DATA!D:D,"300x50",PBL_DA_CAPSTONE_DATA!K:K) -> 4935462 | C78: =SUMIF(PBL_DA_CAPSTONE_DATA!D:D,"300x50",PBL_DA_CAPSTONE_DATA!L:L) -> 14894 | D78: =SUMIF(PBL_DA_CAPSTONE_DATA!D:D,"300x50",PBL_DA_CAPSTONE_DATA!U:U) -> 0 | E78: =IF(B78>0,C78/B78,0) -> 0.0030177519 | H78: Sign up Now - 10% Off | I78: =SUMIF(PBL_DA_CAPSTONE_DATA!E:E,"Sign up Now - 10% Off",PBL_DA_CAPSTONE_DATA!K:K) -> 17150590 | J78: =SUMIF(PBL_DA_CAPSTONE_DATA!E:E,"Sign up Now - 10% Off",PBL_DA_CAPSTONE_DATA!L:L) -> 48516 | K78: =SUMIF(PBL_DA_CAPSTONE_DATA!E:E,"Sign up Now - 10% Off",PBL_DA_CAPSTONE_DATA!U:U) -> 0 | L78: =IF(I78>0,J78/I78,0) -> 0.002828824
H79: 10% Discount - Ends 6/1 | I79: =SUMIF(PBL_DA_CAPSTONE_DATA!E:E,"10% Discount - Ends 6/1",PBL_DA_CAPSTONE_DATA!K:K) -> 25035540 | J79: =SUMIF(PBL_DA_CAPSTONE_DATA!E:E,"10% Discount - Ends 6/1",PBL_DA_CAPSTONE_DATA!L:L) -> 58860 | K79: =SUMIF(PBL_DA_CAPSTONE_DATA!E:E,"10% Discount - Ends 6/1",PBL_DA_CAPSTONE_DATA!U:U) -> 0 | L79: =IF(I79>0,J79/I79,0) -> 0.0023510577
A81: KEY INSIGHTS
A82: 1. Illinois leads in total impressions with the highest volume of ad delivery
A83: 2. Smartphones dominate device distribution, accounting for ~91% of all impressions
A84: 3. Google Ad Manager is the primary ad exchange for campaign delivery (highest viewable and measurable impressions)
A85: 4. Alabama has the highest CTR (0.38%) indicating strong engagement in that state
A86: 5. Apple PC users show the highest CTR among devices (0.32%)
A87: 6. Automotive is the top-performing audience segment by impression volume
A88: 7. The exchange Kargo yielded the greatest results in terms of CPA, CTR, and CVR
A89: 8. The exchange GumGum yielded the greatest results in terms of CPM, vCPM, and CPC
A91: Note: All metrics are calculated dynamically using Excel formulas linked to the source data.

Sheet Pivot Table
B3: CTR | C3: CVR | D3: Viewable Rate | E3: vCPM | F3: CPM | G3: CPC | H3: CPA
A4: Arts and Entertainment
A5: California | B5: 0.0022130112 | C5: 0.020818876 | D5: 0.61139693 | E5: 42.272938 | F5: 23.963141 | G5: 10.828297 | H5: 520.11918
A6: Florida | B6: 0.0039358661 | C6: 0.22105263 | D6: 0.5717074 | E6: 1120.5845 | F6: 598.33834 | G6: 152.02203 | H6: 687.71869
A7: Illinois | B7: 0.0021484172 | C7: 0.057578323 | D7: 0.56607252 | E7: 72.340125 | F7: 34.788748 | G7: 16.192734 | H7: 281.22968
A8: New York | B8: 0.0028682059 | C8: 0.2 | D8: 0.3561147 | E8: 1565.9563 | F8: 352.80615 | G8: 123.00587 | H8: 615.02932
A9: Tennessee | B9: 0.0047094983 | C9: 0.078947368 | D9: 0.37618609 | E9: 1202.6326 | F9: 413.63597 | G9: 87.830156 | H9: 1112.5153
A10: Arts and Entertainment Total | B10: 0.0023036341 | C10: 0.048184595 | D10: 0.58243267 | E10: 106.69219 | F10: 55.325718 | G10: 24.016712 | H10: 498.43134
A11: Automotive
A12: Alabama | B12: 0.0062030464 | C12: 0.088888889 | D12: 0.065269822 | E12: 6375.507 | F12: 380.53547 | G12: 61.346546 | H12: 690.14864
A13: Arkansas | B13: 0.0032192295 | C13: 0.4 | D13: 0.7133149 | E13: 741.90279 | F13: 493.03616 | G13: 153.15347 | H13: 382.88367
A14: California | B14: 0.0029200681 | C14: 0.028247096 | D14: 0.6980998 | E14: 74.064588 | F14: 46.035826 | G14: 15.765326 | H14: 558.12201
A15: Florida | B15: 0.0032648215 | C15: 0.044713439 | D15: 0.5015546 | E15: 227.70621 | F15: 100.2227 | G15: 30.697756 | H15: 686.5443
A16: Georgia | B16: 0.0037758875 | C16: 0.0368 | D16: 0.39808108 | E16: 238.53388 | F16: 78.804201 | G16: 20.870378 | H16: 567.12985
A17: Illinois | B17: 0.0028513436 | C17: 0.02393617 | D17: 0.70811554 | E17: 48.329426 | F17: 28.493048 | G17: 9.9928497 | H17: 417.47905
A18: Indiana | B18: 0.0029766919 | C18: 0.13207547 | D18: 0.57038056 | E18: 599.3288 | F18: 314.05435 | G18: 105.50448 | H18: 798.81967
A19: Michigan | B19: 0.0035694851 | C19: 0.12403101 | D19: 0.528463 | E19: 410.10865 | F19: 185.40925 | G19: 51.942856 | H19: 418.78928
A20: Mississippi | B20: 0.0024703176 | C20: 0.06875 | D20: 0.52530197 | E20: 405.9304 | F20: 56.829253 | G20: 23.004837 | H20: 334.61581
A21: New York | B21: 0.0030898884 | C21: 0.039371119 | D21: 0.52155132 | E21: 100.49153 | F21: 45.228478 | G21: 14.637576 | H21: 371.78462
A22: Tennessee | B22: 0.0026981638 | C22: 0.035033087 | D22: 0.5659583 | E22: 107.3297 | F22: 52.020684 | G22: 19.280032 | H22: 550.3378
A23: Automotive Total | B23: 0.0029589379 | C23: 0.033290789 | D23: 0.63077418 | E23: 89.184785 | F23: 47.884422 | G23: 16.182976 | H23: 486.10972
A24: B2B
A25: California | B25: 0.0027208184 | C25: 0.019972261 | D25: 0.33851883 | E25: 68.434449 | F25: 20.879297 | G25: 7.6739031 | H25: 384.22807
A26: Florida | B26: 0.0027392541 | C26: 0.062116564 | D26: 0.51911895 | E26: 116.67639 | F26: 53.086016 | G26: 19.379734 | H26: 311.9898
A27: Illinois | B27: 0.0026775113 | C27: 0.078023407 | D27: 0.4655921 | E27: 211.66947 | F27: 90.731174 | G27: 33.886383 | H27: 434.31047
A28: Indiana | B28: 0.0028874369 | C28: 0.061326658 | D28: 0.44984559 | E28: 19.80629 | F28: 8.2260422 | G28: 2.848908 | H28: 46.454643
A29: Michigan | B29: 0.0020970503 | C29: 0.11764706 | D29: 0.49301763 | E29: 126.52742 | F29: 55.65388 | G29: 26.539126 | H29: 225.58257
A30: New York | B30: 0.009427494 | C30: 0.045454545 | D30: 0.7139613 | E30: 337.65669 | F30: 227.45814 | G30: 24.127105 | H30: 530.79632
A31: Tennessee | B31: 0.0036855316 | C31: 0.013867488 | D31: 0.48405 | E31: 101.27766 | F31: 44.342263 | G31: 12.031443 | H31: 867.60071
A32: B2B Total | B32: 0.0028163752 | C32: 0.039609333 | D32: 0.41211534 | E32: 98.052276 | F32: 36.424231 | G32: 12.933018 | H32: 326.51442
A33: Beauty and Fitness
A34: California | B34: 0.0028059154 | C34: 0.017564403 | D34: 0.6682192 | E34: 40.048641 | F34: 22.276322 | G34: 7.9390569 | H34: 451.99697
A35: Florida | B35: 0.002748094 | C35: 0.18857143 | D35: 0.63126171 | E35: 341.25249 | F35: 200.36101 | G35: 72.909082 | H35: 386.63907
A36: Illinois | B36: 0.0033085559 | C36: 0.017251816 | D36: 0.58210531 | E36: 31.190486 | F36: 16.263541 | G36: 4.9156011 | H36: 284.93239
A37: New York | B37: 0.0025946245 | C37: 0.059561129 | D37: 0.30690752 | E37: 326.08003 | F37: 89.199152 | G37: 34.378444 | H37: 577.19598
A38: Tennessee | B38: 0.0029969149 | C38: 0.27941176 | D38: 0.51229056 | E38: 706.09934 | F38: 317.79138 | G38: 106.03951 | H38: 379.50982
A39: Beauty and Fitness Total | B39: 0.0031206873 | C39: 0.024610679 | D39: 0.58984594 | E39: 54.569428 | F39: 28.313896 | G39: 9.0729678 | H39: 368.6598
A40: Brand Propensities
A41: Alabama | B41: 0.007650356 | C41: 0.02970297 | D41: 0.84369422 | E41: 156.29296 | F41: 128.69723 | G41: 16.822384 | H41: 566.3536
A42: California | B42: 0.0026923447 | C42: 0.0071455434 | D42: 0.6819242 | E42: 11.421811 | F42: 6.9211701 | G42: 2.570685 | H42: 359.7606
A43: Florida | B43: 0.0027617045 | C43: 0.058139535 | D43: 0.48407377 | E43: 39.917259 | F43: 17.576472 | G43: 6.3643567 | H43: 109.46693
A44: Illinois | B44: 0.0028156071 | C44: 0.01631964 | D44: 0.42184869 | E44: 37.664675 | F44: 13.515539 | G44: 4.8002219 | H44: 294.13773
A45: Indiana | B45: 0.0051348356 | C45: 0.10071942 | D45: 0.73615494 | E45: 188.33437 | F45: 129.84427 | G45: 25.286938 | H45: 251.06317
A46: Louisiana | B46: 0.0029166739 | C46: 0.005988024 | D46: 0.073699534 | E46: 484.95078 | F46: 32.159528 | G46: 11.026096 | H46: 1841.3581
A47: New York | B47: 0.0038960324 | C47: 0.06360424 | D47: 0.50920354 | E47: 96.479462 | F47: 46.020935 | G47: 11.812257 | H47: 185.71492
A48: Ohio | B48: 0.0024150457 | C48: 0.0083333333 | D48: 0.77151024 | E48: 13.099125 | F48: 9.0719256 | G48: 3.7564198 | H48: 450.77038
A49: Tennessee | B49: 0.0025492956 | C49: 0.018429487 | D49: 0.66972139 | E49: 8.0417237 | F49: 4.9315756 | G49: 1.9344856 | H49: 104.96687
A50: Brand Propensities Total | B50: 0.0027595799 | C50: 0.029134607 | D50: 0.57740983 | E50: 25.766349 | F50: 13.357595 | G50: 4.840445 | H50: 166.14073
A51: Buying Channel Preference
A52: Michigan | B52: 0.0053236201 | C52: 0.052631579 | D52: 0.62444246 | E52: 254.58084 | F52: 149.7954 | G52: 28.137882 | H52: 534.61977
A53: Buying Channel Preference Total | B53: 0.0053236201 | C53: 0.052631579 | D53: 0.62444246 | E53: 254.58084 | F53: 149.7954 | G53: 28.137882 | H53: 534.61977
A54: Composite Segment
A55: California | B55: 0.0044189853 | C55: 0.055555556 | D55: 0.62951196 | E55: 207.26093 | F55: 120.98136 | G55: 27.377633 | H55: 492.7974
A56: Composite Segment Total | B56: 0.0044189853 | C56: 0.055555556 | D56: 0.62951196 | E56: 207.26093 | F56: 120.98136 | G56: 27.377633 | H56: 492.7974
A57: Connected Impulse-Shopper Audience
A58: Florida | B58: 0.0041388366 | C58: 0.020689655 | D58: 0.4074671 | E58: 154.01822 | F58: 61.125458 | G58: 14.768754 | H58: 713.8231
A59: Connected Impulse-Shopper Audience Total | B59: 0.0041388366 | C59: 0.020689655 | D59: 0.4074671 | E59: 154.01822 | F59: 61.125458 | G59: 14.768754 | H59: 713.8231
A60: Demographics
A61: California | B61: 0.0017264768 | C61: 0.10714286 | D61: 0.61665905 | E61: 83.889693 | F61: 45.340677 | G61: 26.261968 | H61: 245.1117
A62: Florida | B62: 0.0059152678 | C62: 0.081081081 | D62: 0.48263355 | E62: 347.18071 | F62: 121.86015 | G62: 20.600953 | H62: 254.07842
A63: Illinois | B63: 0.0026115451 | C63: 0.016985138 | D63: 0.46512763 | E63: 25.442908 | F63: 9.5417431 | G63: 3.6536773 | H63: 215.11025
A64: Indiana | B64: 0.0016204328 | C64: 0.094775213 | D64: 0.39175255 | E64: 8.1707796 | F64: 2.8367328 | G64: 1.7506019 | H64: 18.471095
A65: Michigan | B65: 0.0062252405 | C65: 0.034090909 | D65: 0.35282152 | E65: 315.2972 | F65: 104.45224 | G65: 16.778827 | H65: 492.17893
A66: New York | B66: 0.0013594345 | C66: 0.1 | D66: 0.22404063 | E66: 1089.6559 | F66: 235.23295 | G66: 173.03736 | H66: 1730.3736
A67: Tennessee | B67: 0.0034906536 | C67: 0.054466231 | D67: 0.55341313 | E67: 125.42917 | F67: 58.478414 | G67: 16.752855 | H67: 307.58242
A68: Demographics Total | B68: 0.0022354526 | C68: 0.064109036 | D68: 0.43636685 | E68: 51.139517 | F68: 19.243669 | G68: 8.6083993 | H68: 134.27747
A69: Demographics Validated
A70: California | B70: 0.0032956381 | C70: 0.090497738 | D70: 0.51233099 | E70: 386.25459 | F70: 167.04323 | G70: 50.686157 | H70: 560.08203
A71: Florida | B71: 0.0026977651 | C71: 0.017790262 | D71: 0.51339289 | E71: 52.237807 | F71: 23.739881 | G71: 8.7998327 | H71: 494.64323
A72: Georgia | B72: 0.0025268835 | C72: 0.030120482 | D72: 0.65438753 | E72: 378.2319 | F72: 24.166769 | G72: 9.5638637 | H72: 317.52027
A73: Illinois | B73: 0.0027654073 | C73: 0.032520325 | D73: 0.54125787 | E73: 80.455014 | F73: 37.348414 | G73: 13.505574 | H73: 415.29641
A74: Michigan | B74: 0.0030621306 | C74: 0.034 | D74: 0.3177363 | E74: 253.56478 | F74: 67.909738 | G74: 22.177283 | H74: 652.27304
A75: New York | B75: 0.0026182976 | C75: 0.075590551 | D75: 0.50267759 | E75: 90.949274 | F75: 42.276914 | G75: 16.146719 | H75: 213.60763
A76: Tennessee | B76: 0.0048624633 | C76: 0.11725664 | D76: 0.48604027 | E76: 648.55005 | F76: 283.24049 | G76: 58.250412 | H76: 496.7771
A77: Demographics Validated Total | B77: 0.0027904288 | C77: 0.036114685 | D77: 0.51410379 | E77: 110.30623 | F77: 44.406036 | G77: 15.913696 | H77: 440.64335
A78: Demos
A79: California | B79: 0.003249555 | C79: 0.078838174 | D79: 0.40991476 | E79: 75.776824 | F79: 25.64993 | G79: 7.8933668 | H79: 100.12113
A80: Florida | B80: 0.0024000193 | C80: 0.060301508 | D80: 0.32264363 | E80: 63.517342 | F80: 19.113575 | G80: 7.9639256 | H80: 132.06843
A81: Michigan | B81: 0.0043695381 | C81: 0.040816327 | D81: 0.53793708 | E81: 281.43929 | F81: 138.61149 | G81: 31.722229 | H81: 777.1946
A82: South Carolina | B82: 0.0039620798 | C82: 0.01369863 | D82: 0.9279961 | E82: 32.212301 | F82: 27.730179 | G82: 6.9988945 | H82: 510.9193
A83: Demos Total | B83: 0.0031668217 | C83: 0.050847458 | D83: 0.51550343 | E83: 63.728247 | F83: 29.40613 | G83: 9.2856917 | H83: 182.6186
A84: Device Ownership
A85: California | B85: 0.002723905 | C85: 0.08 | D85: 0.54880643 | E85: 323.6876 | F85: 163.78353 | G85: 60.128208 | H85: 751.6026
A86: Florida | B86: 0.0026055675 | C86: 0.092473118 | D86: 0.54668254 | E86: 72.883094 | F86: 36.378247 | G86: 13.961736 | H86: 150.98157
A87: New York | B87: 0.0024816135 | C87: 0.054545455 | D87: 0.29126691 | E87: 630.81896 | F87: 67.399689 | G87: 27.159624 | H87: 497.92643
A88: Tennessee | B88: 0.0022669311 | C88: 0.375 | D88: 0.64110551 | E88: 164.55828 | F88: 90.210949 | G88: 39.794305 | H88: 106.11815
A89: Device Ownership Total | B89: 0.0025719938 | C89: 0.10769231 | D89: 0.54342543 | E89: 104.77264 | F89: 48.718242 | G89: 18.941819 | H89: 175.88832
A90: Entertainment and Pastimes
A91: Florida | B91: 0.00234055 | C91: 0.1 | D91: 0.62686025 | E91: 631.51358 | F91: 255.26599 | G91: 109.06239 | H91: 1090.6239
A92: Entertainment and Pastimes Total | B92: 0.00234055 | C92: 0.1 | D92: 0.62686025 | E92: 631.51358 | F92: 255.26599 | G92: 109.06239 | H92: 1090.6239
A93: Finance
A94: California | B94: 0.0025632179 | C94: 0.052404882 | D94: 0.75455874 | E94: 51.999102 | F94: 35.966291 | G94: 14.031695 | H94: 267.75549
A95: Florida | B95: 0.0027501671 | C95: 0.01926851 | D95: 0.53253952 | E95: 40.243474 | F95: 19.856015 | G95: 7.2199306 | H95: 374.70103
A96: Georgia | B96: 0.0027048959 | C96: 0.05 | D96: 0.51643404 | E96: 472.20017 | F96: 219.75126 | G96: 81.24204 | H96: 1624.8408
A97: Illinois | B97: 0.0016080692 | C97: 0.045354056 | D97: 0.63090118 | E97: 15.504419 | F97: 8.5156792 | G97: 5.2955927 | H97: 116.76117
A98: Louisiana | B98: 0.0027303639 | C98: 0.010309278 | D98: 0.73917034 | E98: 20.932539 | F98: 8.350885 | G98: 3.0585245 | H98: 296.67688
A99: Mississippi | B99: 0.0025027689 | C99: 0.051724138 | D99: 0.73363222 | E99: 54.896066 | F99: 38.116851 | G99: 15.229872 | H99: 294.4442
A100: New York | B100: 0.0022446878 | C100: 0.1329588 | D100: 0.17527921 | E100: 257.11683 | F100: 40.098747 | G100: 17.863842 | H100: 134.35622
A101: Tennessee | B101: 0.0038027869 | C101: 0.058566434 | D101: 0.75515078 | E101: 117.19503 | F101: 76.747566 | G101: 20.181926 | H101: 344.59886
A102: Finance Total | B102: 0.0019449564 | C102: 0.042220058 | D102: 0.62140847 | E102: 27.313022 | F102: 14.922794 | G102: 7.6725594 | H102: 181.72782
...

Sheet Sheet2
A3: Row Labels | B3: CPM | C3: vCPM | D3: CPA | E3: CVR | F3: CTR | G3: CPC | H3: Viewable Rate | I3: Total Viewable Imp. | J3: Total Measurable Imp. | L3: Top 5 CPA
A4: Kargo | L4: Kargo
A5: mlb.com | B5: 127.86021 | C5: 218.51995 | D5: 113.78646 | E5: 0.16666667 | F5: 0.0067421141 | G5: 18.96441 | H5: 0.6214304 | I5: 7290 | J5: 11731 | L5: Xandr - Monetize SSP (AppNexus)
A6: Xandr - Monetize SSP (AppNexus) | L6: Sovrn
A7: mail.yahoo.com | B7: 6.1861863 | C7: 11.093801 | D7: 66.561907 | E7: 0.03602812 | F7: 0.0025796195 | G7: 2.3981003 | H7: 0.62655207 | I7: 737990 | J7: 1177859 | L7: Taboola
A8: ebay.com | B8: 12.526347 | C8: 20.783073 | D8: 91.405555 | E8: 0.05760709 | F8: 0.0023788984 | G8: 5.2656081 | H8: 0.63394766 | I8: 343050 | J8: 541133 | L8: TripleLift
A9: yahoo.com | B9: 16.223486 | C9: 44.254281 | D9: 604.0193 | E9: 0.0096385542 | F9: 0.0027866438 | G9: 5.8218728 | H9: 0.43779469 | I9: 163786 | J9: 374116 | L9: PulsePoint
A10: outlook.live.com | B10: 42.915842 | C10: 50.647106 | D10: 231.27852 | E10: 0.051051051 | F10: 0.003634776 | G10: 11.807012 | H10: 0.91553988 | I10: 155260 | J10: 169583
A11: msn.com | B11: 9.6653498 | C11: 16.340343 | D11: 207.29155 | E11: 0.016032064 | F11: 0.0029083491 | G11: 3.3233114 | H11: 0.74603046 | I11: 101487 | J11: 136036
A12: nypost.com | B12: 43.421988 | C12: 80.056046 | D12: 234.41026 | E12: 0.073863636 | F12: 0.0025078549 | G12: 17.314394 | H12: 0.56992918 | I12: 76130 | J12: 133578
A13: baseball-reference.com | B13: 21.284 | C13: 153.17011 | D13: 501.0807 | E13: 0.013368984 | F13: 0.0031772192 | G13: 6.6989398 | H13: 0.16320768 | I13: 16357 | J13: 100222
A14: pandora.com | B14: 89.738254 | C14: 120.48546 | D14: 276.19073 | E14: 0.14074074 | F14: 0.0023086 | G14: 38.871288 | H14: 0.77007674 | I14: 43554 | J14: 56558
A15: dailyhodl.com | B15: 92.354833 | C15: 115.63744 | D15: 3621.4177 | E15: 0.0038461538 | F15: 0.0066306233 | G15: 13.92853 | H15: 0.83157196 | I15: 31317 | J15: 37660
A16: moneyppl.com | B16: 40.133674 | C16: 160.93404 | D16: 123.99968 | E16: 0.10619469 | F16: 0.0030477937 | G16: 13.168107 | H16: 0.40974961 | I16: 9246 | J16: 22565
A17: ajc.com | B17: 274.72416 | C17: 565.0699 | D17: 489.9156 | E17: 0.16393443 | F17: 0.0034206247 | G17: 80.314033 | H17: 0.51389959 | I17: 8670 | J17: 16871
A18: dotesports.com | B18: 224.78963 | C18: 381.53689 | D18: 270.07725 | E18: 0.5 | F18: 0.0016646321 | G18: 135.03862 | H18: 0.63798594 | I18: 10618 | J18: 16643
A19: washingtonpost.com | B19: 693.17615 | C19: 996.0054 | D19: 569.96409 | E19: 0.4 | F19: 0.0030404378 | G19: 227.98564 | H19: 0.73467423 | I19: 6867 | J19: 9347
A20: ew.com | B20: 146.48331 | C20: 216.81802 | D20: 145.31144 | E20: 0.5 | F20: 0.002016129 | G20: 72.65572 | H20: 0.73680739 | I20: 6702 | J20: 9096
A21: accuweather.com | B21: 594.65936 | C21: 1513.4556 | D21: 780.56474 | E21: 0.088888889 | F21: 0.0085706123 | G21: 69.383532 | H21: 0.53906454 | I21: 4126 | J21: 7654
... A23: fandom.com | B23: 407.2384 | C23: 2886.2454 | D23: 887.3143 | E23: 0.12727273 | F23: 0.0036060844 | G23: 112.93091 | H23: 0.61803561 | I23: 2152 | J23: 3482
A24: Sovrn
A25: realtor.com | B25: 23.446438 | C25: 43.946495 | D25: 535.83082 | E25: 0.045454545 | F25: 0.00096265764 | G25: 24.355946 | H25: 0.56291262 | I25: 60964 | J25: 108301
A26: cars.com | B26: 28.411304 | C26: 48.229503 | D26: 315.14765 | E26: 0.035502959 | F26: 0.0025392914 | G26: 11.188674 | H26: 0.63124507 | I26: 39206 | J26: 62109
A27: finance.yahoo.com | B27: 43.39611 | C27: 89.803494 | D27: 553.90795 | E27: 0.033333333 | F27: 0.0023503604 | G27: 18.463598 | H27: 0.541492 | I27: 24672 | J27: 45563
A28: screenrant.com | B28: 43.602896 | C28: 72.962291 | D28: 63.665679 | E28: 0.17142857 | F28: 0.0039950917 | G28: 10.914116 | H28: 0.62552645 | I28: 20942 | J28: 33479
A29: m.timesofindia.com | B29: 114.79664 | C29: 242.68586 | D29: 912.86285 | E29: 0.010526316 | F29: 0.01194668 | G29: 9.6090826 | H29: 0.50779615 | I29: 7523 | J29: 14815
A30: Taboola
A31: mail.yahoo.com | B31: 5.7003995 | C31: 8.0364689 | D31: 161.90898 | E31: 0.016129032 | F31: 0.0021828608 | G31: 2.6114352 | H31: 0.75494634 | I31: 644697 | J31: 853964
A32: zillow.com | B32: 11.54536 | C32: 128.4805 | D32: 376.96177 | E32: 0.014869888 | F32: 0.0020596928 | G32: 5.6053796 | H32: 0.10318723 | I32: 11736 | J32: 113735
A33: finance.yahoo.com | B33: 20.41755 | C33: 38.708933 | D33: 101.30644 | E33: 0.1 | F33: 0.0020154247 | G33: 10.130644 | H33: 0.58460782 | I33: 39257 | J33: 67151
A34: biblegateway.com | B34: 120.23656 | C34: 364.48334 | D34: 434.52489 | E34: 0.10810811 | F34: 0.0025595499 | G34: 46.975664 | H34: 0.35989937 | I34: 14306 | J34: 39750
A35: reuters.com | B35: 90.674308 | C35: 133.53028 | D35: 507.5041 | E35: 0.075 | F35: 0.0023822286 | G35: 38.062808 | H35: 0.80120863 | I35: 11402 | J35: 14231
A36: androidpolice.com | B36: 227.45814 | C36: 337.65669 | D36: 530.79632 | E36: 0.045454545 | F36: 0.009427494 | G36: 24.127105 | H36: 0.7139613 | I36: 7860 | J36: 11009
A37: TripleLift
A38: taboolanews.com | B38: 6.665053 | C38: 19.334503 | D38: 90.738031 | E38: 0.028571429 | F38: 0.0025708829 | G38: 2.5925152 | H38: 0.41780407 | I38: 75089 | J38: 179723
A39: cbsnews.com | B39: 44.795921 | C39: 57.93336 | D39: 48.324765 | E39: 0.27777778 | F39: 0.0033371154 | G39: 13.423546 | H39: 0.81161361 | I39: 104268 | J39: 128470
A40: msn.com | B40: 51.055956 | C40: 90.282491 | D40: 5999.9938 | E40: 0.0033444816 | F40: 0.0025442911 | G40: 20.066869 | H40: 0.76767047 | I40: 66458 | J40: 86571
A41: forbes.com | B41: 64.405999 | C41: 123.31734 | D41: 515.3768 | E41: 0.02972973 | F41: 0.0042034946 | G41: 15.322013 | H41: 0.54779438 | I41: 45972 | J41: 83922
A42: news.yahoo.com | B42: 163.55198 | C42: 325.29386 | D42: 754.3926 | E42: 0.079646018 | F42: 0.0027220389 | G42: 60.084366 | H42: 0.5317707 | I42: 20872 | J42: 39250
A43: yahoo.com | B43: 51.067631 | C43: 140.38508 | D43: 475.27368 | E43: 0.030769231 | F43: 0.0034920891 | G43: 14.623805 | H43: 0.4172418 | I43: 13542 | J43: 32456
A44: businessinsider.com | B44: 532.83974 | C44: 784.06381 | D44: 3175.4585 | E44: 0.028985507 | F44: 0.0057890763 | G44: 92.042274 | H44: 0.70288094 | I44: 8100 | J44: 11524
A45: newsharper.com | B45: 124.64039 | C45: 382.75692 | D45: 676.71423 | E45: 0.053571429 | F45: 0.0034381139 | G45: 36.252548 | H45: 0.49426894 | I45: 5304 | J45: 10731
A46: si.com | B46: 165.37774 | C46: 470.5715 | D46: 382.3864 | E46: 0.057471264 | F46: 0.0075253006 | G46: 21.97623 | H46: 0.4087114 | I46: 4063 | J46: 9941
A47: buzzfeed.com | B47: 148.93223 | C47: 246.60488 | D47: 420.58463 | E47: 0.074074074 | F47: 0.0047804533 | G47: 31.154417 | H47: 0.73560492 | I47: 6822 | J47: 9274
A48: cnet.com | B48: 669.15194 | C48: 921.49124 | D48: 1679.5714 | E48: 0.15 | F48: 0.0026560425 | G48: 251.93571 | H48: 0.74924637 | I48: 5468 | J48: 7298
A49: signin.ebay.com | B49: 222.89122 | C49: 356.76972 | D49: 940.2666 | E49: 0.031746032 | F49: 0.0074671092 | G49: 29.849733 | H49: 0.74607219 | I49: 5271 | J49: 7065
A50: PulsePoint
A51: foxnews.com | B51: 42.263606 | C51: 84.375158 | D51: 295.49868 | E51: 0.040983607 | F51: 0.0034898023 | G51: 12.110602 | H51: 0.54766373 | I51: 17511 | J51: 31974
A52: microsoftcasualgames.com | B52: 6.24216 | C52: 282.10051 | D52: 456.57968 | E52: 0.0049261084 | F52: 0.0027753283 | G52: 2.249161 | H52: 0.52535908 | I52: 6474 | J52: 12323
A53: classmates.com | B53: 149.14839 | C53: 332.60637 | D53: 181.60308 | E53: 1 | F53: 0.00082128778 | G53: 181.60308 | H53: 0.48951049 | I53: 5460 | J53: 11154
A54: Smart RTB+ (Smartadserver)
A55: mail.yahoo.com | B55: 2.1755695 | C55: 3.1587402 | D55: 164.15832 | E55: 0.0045362903 | F55: 0.0029215224 | G55: 0.74466981 | H55: 0.73705343 | I55: 467726 | J55: 634589
A56: weather.com | B56: 22.293283 | C56: 101.69636 | D56: 139.47474 | E56: 0.047098402 | F56: 0.003393691 | G56: 6.5690373 | H56: 0.30139744 | I56: 76803 | J56: 254823
A57: msn.com | B57: 13.25303 | C57: 25.92891 | D57: 889.17492 | E57: 0.005192108 | F57: 0.0028706765 | G57: 4.6166922 | H57: 0.69292382 | I57: 171464 | J57: 247450
A58: cbsnews.com | B58: 26.445035 | C58: 64.047216 | D58: 122.59918 | E58: 0.073529412 | F58: 0.0029335634 | G58: 9.0146456 | H58: 0.45700234 | I58: 28713 | J58: 62829
A59: drugs.com | B59: 29.771845 | C59: 59.581067 | D59: 490.3919 | E59: 0.020833333 | F59: 0.0029140949 | G59: 10.216498 | H59: 0.54190717 | I59: 24692 | J59: 45565
A60: boxrox.com | B60: 61.125458 | C60: 154.01822 | D60: 713.8231 | E60: 0.020689655 | F60: 0.0041388366 | G60: 14.768754 | H60: 0.4074671 | I60: 13904 | J60: 34123
A61: mail.aol.com | B61: 218.12103 | C61: 304.35027 | D61: 265.75866 | E61: 0.26315789 | F61: 0.0031188444 | G61: 69.936489 | H61: 0.78666667 | I61: 21830 | J61: 27750
A62: rollingstone.com | B62: 377.1664 | C62: 840.78578 | D62: 662.92137 | E62: 0.275 | F62: 0.0020688942 | G62: 182.30338 | H62: 0.4668425 | I62: 8673 | J62: 18578
A63: biblegateway.com | B63: 79.557375 | C63: 153.66883 | D63: 364.23355 | E63: 0.066666667 | F63: 0.0032763611 | G63: 24.282237 | H63: 0.58165644 | I63: 9481 | J63: 16300
A64: npr.org | B64: 114.41378 | C64: 200.73733 | D64: 1555.1121 | E64: 0.011764706 | F64: 0.0062536786 | G64: 18.295436 | H64: 0.72469598 | I64: 7747 | J64: 10690
A65: OpenX
A66: msn.com | B66: 1.8009559 | C66: 2.8590884 | D66: 82.232446 | E66: 0.008004574 | F66: 0.002736035 | G66: 0.6582357 | H66: 0.75430735 | I66: 2013324 | J66: 2669103
A67: the-sun.com | B67: 30.877212 | C67: 47.801277 | D67: 238.43576 | E67: 0.042666667 | F67: 0.0030351347 | G67: 10.173259 | H67: 0.68461505 | I67: 159618 | J67: 233150
A68: lotterypost.com | B68: 24.880624 | C68: 164.05064 | D68: 189.68191 | E68: 0.041597338 | F68: 0.0031533328 | G68: 7.8902626 | H68: 0.16755644 | I68: 28906 | J68: 172515
A69: fandomwire.com | B69: 58.324793 | C69: 161.37736 | D69: 310.02127 | E69: 0.03559322 | F69: 0.0052856017 | G69: 11.034655 | H69: 0.39822913 | I69: 40343 | J69: 101306
A70: a-z-animals.com | B70: 20.043122 | C70: 37.302491 | D70: 502.1537 | E70: 0.010714286 | F70: 0.0037253363 | G70: 5.3802182 | H70: 0.57426235 | I70: 40385 | J70: 70325
A71: foxnews.com | B71: 19.462026 | C71: 34.557719 | D71: 165.91161 | E71: 0.048128342 | F71: 0.0024373078 | G71: 7.9850508 | H71: 0.62144398 | I71: 43209 | J71: 69530
A72: accuweather.com | B72: 49.792972 | C72: 108.64686 | D72: 151.02858 | E72: 0.13939394 | F72: 0.0023651845 | G72: 21.052468 | H72: 0.52843661 | I72: 31972 | J72: 60503
A73: kbb.com | B73: 74.026731 | C73: 119.55406 | D73: 604.72437 | E73: 0.06 | F73: 0.0020402334 | G73: 36.283462 | H73: 0.65342548 | I73: 30349 | J73: 46446
A74: finance.yahoo.com | B74: 152.03854 | C74: 356.26154 | D74: 422.90471 | E74: 0.128 | F74: 0.0028086732 | G74: 54.131803 | H74: 0.48056779 | I74: 18993 | J74: 39522
A75: usatoday.com | B75: 127.08174 | C75: 489.34276 | D75: 459.60578 | E75: 0.065326633 | F75: 0.0042326017 | G75: 30.024498 | H75: 0.32098636 | I75: 12210 | J75: 38039
A76: redfin.com | B76: 42.770104 | C76: 315.96288 | D76: 268.14717 | E76: 0.070588235 | F76: 0.0022596167 | G76: 18.928035 | H76: 0.14813953 | I76: 5092 | J76: 34373
A77: alotfinance.com | B77: 125.69254 | C77: 305.1003 | D77: 423.65719 | E77: 0.06779661 | F77: 0.0043760971 | G77: 28.722521 | H77: 0.55964936 | I77: 16663 | J77: 29774
... A93: bleacherbreaker.com | B93: 187.35357 | C93: 419.84589 | D93: 1700.7957 | E93: 0.047619048 | F93: 0.0023132849 | G93: 80.990271 | H93: 0.65181014 | I93: 4051 | J93: 6215
A94: PubMatic
A95: msn.com | B95: 4.4418023 | C95: 7.3894284 | D95: 131.77297 | E95: 0.030936694 | F95: 0.0010895796 | G95: 4.0766202 | H95: 0.70430552 | I95: 3851849 | J95: 5469003
A96: mail.yahoo.com | B96: 7.4038093 | C96: 15.189053 | D96: 222.57615 | E96: 0.011913104 | F96: 0.002792233 | G96: 2.6515729 | H96: 0.62182978 | I96: 996453 | J96: 1602453
A97: yahoo.com | B97: 7.1059867 | C97: 17.292022 | D97: 124.78294 | E97: 0.017795533 | F97: 0.0032000604 | G97: 2.2205789 | H97: 0.4542864 | I97: 707189 | J97: 1556703
A98: weather.com | B98: 21.175087 | C98: 104.10221 | D98: 248.28567 | E98: 0.028851244 | F98: 0.0029560312 | G98: 7.1633505 | H98: 0.2398713 | I98: 259967 | J98: 1083777
A99: mail.aol.com | B99: 49.934312 | C99: 66.689383 | D99: 452.19847 | E99: 0.040106952 | F99: 0.0027532796 | G99: 18.136302 | H99: 0.81956117 | I99: 101710 | J99: 124103
A100: espn.com | B100: 32.733682 | C100: 92.695155 | D100: 998.30365 | E100: 0.010840108 | F100: 0.0030248133 | G100: 10.82172 | H100: 0.43377437 | I100: 43079 | J100: 99312
A101: finance.yahoo.com | B101: 14.755489 | C101: 28.058221 | D101: 323.34294 | E101: 0.014492754 | F101: 0.0031487583 | G101: 4.6861296 | H101: 0.58854172 | I101: 57620 | J101: 97903
A102: cheapoair.com | B102: 41.334419 | C102: 324.28425 | D102: 790.33477 | E102: 0.017142857 | F102: 0.0030508268 | G102: 13.548596 | H102: 0.15883688 | I102: 14623 | J102: 92063
A103: fandomwire.com | B103: 58.422522 | C103: 420.32223 | D103: 620.86263 | E103: 0.0375 | F103: 0.0025093053 | G103: 23.282349 | H103: 0.15320081 | I103: 13294 | J103: 86775
A104: nypost.com | B104: 21.305288 | C104: 54.422434 | D104: 783.68305 | E104: 0.010152284 | F104: 0.0026778311 | G104: 7.9561731 | H104: 0.42003325 | I104: 28800 | J104: 68566
A105: news.yahoo.com | B105: 19.931909 | C105: 36.279478 | D105: 1465.8723 | E105: 0.0044843049 | F105: 0.0030321984 | G105: 6.5734184 | H105: 0.59942735 | I105: 40405 | J105: 67406
A106: ebay.com | B106: 40.808663 | C106: 148.00068 | D106: 1017.0607 | E106: 0.010416667 | F106: 0.0038519153 | G106: 10.594382 | H106: 0.31448882 | I106: 20616 | J106: 65554
... A147: microsoftcasualgames.com | B147: 55.962179 | C147: 6468.1593 | D147: 369.7631 | E147: 0.063492063 | F147: 0.0023837 | G147: 23.477022 | H147: 0.30327144 | I147: 1372 | J147: 4524
A148: Yieldmo
A149: ebay.com | B149: 79.225252 | C149: 4684.1651 | D149: 350.07971 | E149: 0.1027027 | F149: 0.0022035089 | G149: 35.954132 | H149: 0.0205066 | I149: 1420 | J149: 69246
A150: people.com | B150: 86.100451 | C150: 128.05349 | D150: 318.21292 | E150: 0.042857143 | F150: 0.006313416 | G150: 13.637696 | H150: 0.74275182 | I150: 14910 | J150: 20074
A151: merriam-webster.com | B151: 159.36846 | C151: 243.52302 | D151: 215.112 | E151: 0.225 | F151: 0.0032927231 | G151: 48.4002 | H151: 0.69982394 | I151: 7950 | J151: 11360
A152: tripadvisor.com | B152: 427.48297 | C152: 755.58851 | D152: 295.98921 | E152: 0.23076923 | F152: 0.0062584248 | G152: 68.305202 | H152: 0.58479299 | I152: 5876 | J152: 10048
A153: buzzfeed.com | B153: 683.44795 | C153: 985.89669 | D153: 362.08353 | E153: 0.3015873 | F153: 0.0062586926 | G153: 109.1998 | H153: 0.74479667 | I153: 6978 | J153: 9369
A154: healthyrecipesblogs.com | B154: 192.1629 | C154: 384.87268 | D154: 439.5246 | E154: 0.1 | F154: 0.0043720625 | G154: 43.95246 | H154: 0.52821462 | I154: 4568 | J154: 8648
A155: lensvid.com | B155: 170.80105 | C155: 304.63013 | D155: 384.90017 | E155: 0.15384615 | F155: 0.002884402 | G155: 59.215412 | H155: 0.69932199 | I155: 5054 | J155: 7227
A156: BidSwitch
A157: mail.yahoo.com | B157: 6.4976649 | C157: 12.434207 | D157: 121.5164 | E157: 0.021342819 | F157: 0.0025053629 | G157: 2.5935024 | H157: 0.59434256 | I157: 1407276 | J157: 2367786
A158: yahoo.com | B158: 13.171379 | C158: 32.933105 | D158: 141.11092 | E158: 0.040561147 | F158: 0.0023012319 | G158: 5.7236209 | H158: 0.44571871 | I158: 569875 | J158: 1278553
...

Sheet PBL_DA_CAPSTONE_DATA
A1: Audience Segment | B1: Category | C1: Sub Category | D1: Creative Size | E1: Creative Messaging | F1: City | G1: State | H1: App/URL | I1: Exchange | J1: Device Make | K1: Impressions | L1: Clicks | M1: Viewable Impressions | N1: Measurable Impressions | O1: Total Conversions | P1: Gross Cost
A2: Arts and Entertainment | B2: Arts and Entertainment | D2: 320x50 | E2: Subscribe Today - 10% Discount | F2: Orlando-Daytona Beach | G2: Florida | H2: nbcchicago.com | I2: Google Ad Manager | J2: Smartphone | K2: 7248 | L2: 10 | M2: 3988 | N2: 6863 | O2: 7 | P2: 1247
A3: Arts and Entertainment | B3: Celebrities and Entertainment News | D3: 320x50 | E3: 10% Discount - Ends 6/1 | F3: Orlando-Daytona Beach | G3: Florida | H3: icy-veins.com | I3: Google Ad Manager | J3: Smartphone | K3: 9261 | L3: 66 | M3: 3852 | N3: 8526 | O3: 9 | P3: 6511.0296
A4: Arts and Entertainment | B4: Comics and Animation | D4: 300x250 | E4: Subscribe Today - 10% Discount | F4: Knoxville | G4: Tennessee | H4: fox59.com | I4: Google Ad Manager | J4: Smartphone | K4: 7583 | L4: 45 | M4: 4608 | N4: 5881 | O4: 1 | P4: 5033.4826
A5: Arts and Entertainment | B5: Events and Listings | C5: Clubs and Nightlife | D5: 300x250 | E5: 10% Discount - Ends 6/1 | F5: Chicago | G5: Illinois | H5: activebeat.com | I5: Magnite DV+ | J5: Windows PC | K5: 81905 | L5: 220 | M5: 61995 | N5: 71110 | O5: 24 | P5: 7065.6693
A6: Arts and Entertainment | B6: Events and Listings | C6: Concerts and Music Festivals | D6: 300x50 | E6: Sign up Today - 10% Off | F6: Chicago | G6: Illinois | H6: usssa.com | I6: Google Ad Manager | J6: Smartphone | K6: 446774 | L6: 951 | M6: 196581 | N6: 379758 | O6: 33 | P6: 6956.6274
A7: Arts and Entertainment | B7: Events and Listings | C7: Event Ticket Sales | D7: 300x50 | E7: Sign up Today - 10% Off | F7: Nashville | G7: Tennessee | H7: wikihow.com | I7: Magnite DV+ | J7: Smartphone | K7: 23488 | L7: 75 | M7: 4620 | N7: 22254 | O7: 9 | P7: 6667.7277
A8: Arts and Entertainment | B8: Events and Listings | C8: Expos and Conventions | D8: 300x250 | E8: Subscribe Today - 10% Discount | F8: Los Angeles | G8: California | H8: zillow.com | I8: Google Ad Manager | J8: Apple PC | K8: 20833 | L8: 87 | M8: 1777 | N8: 17211 | O8: 9 | P8: 5542.5122
A9: Arts and Entertainment | B9: Events and Listings | C9: Film Festivals | D9: 320x50 | E9: Sign up Now - 10% Off | F9: Los Angeles | G9: California | H9: ebay.com | I9: Google Ad Manager | J9: Smartphone | K9: 405957 | L9: 874 | M9: 204189 | N9: 385654 | O9: 16 | P9: 5864.1265
A10: Arts and Entertainment | B10: Events and Listings | C10: Food and Beverage Events | D10: 300x250 | E10: Sign up Today - 10% Off | F10: Los Angeles | G10: California | H10: mail.aol.com | I10: Google Ad Manager | J10: Smartphone | K10: 224359 | L10: 480 | M10: 163149 | N10: 200859 | O10: 5 | P10: 4196.9368
A11: Arts and Entertainment | B11: Events and Listings | C11: Live Sporting Events | D11: 320x50 | E11: Subscribe Today - 10% Discount | F11: Chicago | G11: Illinois | H11: my.yahoo.com | I11: Google Ad Manager | J11: Smartphone | K11: 21028 | L11: 10 | M11: 5781 | N11: 16134 | O11: 11 | P11: 5101.3217
A12: Arts and Entertainment | B12: Movies | D12: 300x250 | E12: 10% Discount - Ends 6/1 | F12: Nashville | G12: Tennessee | H12: funnyand.com | I12: Google Ad Manager | J12: Smartphone | K12: 9273 | L12: 70 | M12: 4648 | N12: 8751 | O12: 5 | P12: 4986.5194
A13: Arts and Entertainment | B13: Music and Audio | D13: 300x250 | E13: Sign up Today - 10% Off | F13: Jacksonville | G13: Florida | H13: chicagotribune.com | I13: Google Ad Manager | J13: Smartphone | K13: 7628 | L13: 19 | M13: 5048 | N13: 7154 | O13: 5 | P13: 6684.0628
A14: Arts and Entertainment | B14: TV and Video | D14: 300x50 | E14: Subscribe Today - 10% Discount | F14: New York City | G14: New York | H14: msn.com | I14: BidSwitch | J14: Smartphone | K14: 13946 | L14: 40 | M14: 3142 | N14: 8823 | O14: 8 | P14: 4920.2346
A15: Automotive | B15: Auto Buyers | C15: Audi Q | D15: 300x250 | E15: Sign up Now - 10% Off | F15: Grand Rapids-Kalamazoo | G15: Michigan | H15: accuweather.com | I15: Xandr - Monetize SSP (AppNexus) | J15: Smartphone | K15: 10501 | L15: 90 | M15: 4126 | N15: 7654 | O15: 8 | P15: 6244.5179
A16: Automotive | B16: Auto Buyers | C16: BMW | D16: 300x250 | E16: Sign up Today - 10% Off | F16: West Palm Beach-Ft. Pierce | G16: Florida | H16: firstcoastnews.com | I16: BidSwitch | J16: Smartphone | K16: 12092 | L16: 30 | M16: 2042 | N16: 10315 | O16: 8 | P16: 6245.1348
A17: Automotive | B17: Auto Buyers | C17: Dodge | D17: 320x50 | E17: Subscribe Today - 10% Discount | F17: Champaign & Springfield-Decatur | G17: Illinois | H17: historycollection.com | I17: Google Ad Manager | J17: Smartphone | K17: 138904 | L17: 399 | M17: 98952 | N17: 120688 | O17: 25 | P17: 5038.6447
A18: Automotive | B18: Auto Buyers | C18: Ford | D18: 300x250 | E18: 10% Discount - Ends 6/1 | F18: Nashville | G18: Tennessee | H18: foxnews.com | I18: BidSwitch | J18: Apple PC | K18: 29323 | L18: 88 | M18: 13822 | N18: 26934 | O18: 9 | P18: 6096.0455
A19: Automotive | B19: Auto Buyers | C19: Honda | D19: 300x250 | E19: Subscribe Today - 10% Discount | F19: Nashville | G19: Tennessee | H19: npr.org | I19: Yahoo Exchange | J19: Smartphone | K19: 8000 | L19: 10 | M19: 4400 | N19: 6379 | O19: 1 | P19: 6159.3669
A20: Automotive | B20: Auto Buyers | C20: Hyundai | D20: 320x50 | E20: 10% Discount - Ends 6/1 | F20: New York City | G20: New York | H20: daily-choices.com | I20: OpenX | J20: Smartphone | K20: 25532 | L20: 140 | M20: 15219 | N20: 21497 | O20: 9 | P20: 6047.1741
A21: Automotive | B21: Auto Buyers | C21: Jeep | D21: 300x250 | E21: Sign up Today - 10% Off | F21: New York City | G21: New York | H21: weather.com | I21: Smart RTB+ (Smartadserver) | J21: Windows PC | K21: 96779 | L21: 299 | M21: 9831 | N21: 63640 | O21: 12 | P21: 6317.5108
A22: Automotive | B22: Auto Buyers | C22: Mazda | D22: 300x250 | E22: 10% Discount - Ends 6/1 | F22: Miami-Ft. Lauderdale | G22: Florida | H22: iflscience.com | I22: Google Ad Manager | J22: Smartphone | K22: 11672 | L22: 84 | M22: 7619 | N22: 9999 | O22: 7 | P22: 5284.277
A23: Automotive | B23: Auto Buyers | C23: Mercedes | D23: 320x50 | E23: Subscribe Today - 10% Discount | F23: Lansing | G23: Michigan | H23: realtor.com | I23: Index Exchange | J23: Smartphone | K23: 42459 | L23: 121 | M23: 15187 | N23: 37408 | O23: 11 | P23: 6321.4917
A24: Automotive | B24: Auto Buyers | C24: Nissan | D24: 320x50 | E24: Subscribe Today - 10% Discount | F24: Miami-Ft. Lauderdale | G24: Florida | H24: britannica.com | I24: Google Ad Manager | J24: Smartphone | K24: 8068 | L24: 10 | M24: 5545 | N24: 7554 | O24: 1 | P24: 5995.041
A25: Automotive | B25: Auto Buyers | C25: Opel | D25: 300x250 | E25: Subscribe Today - 10% Discount | F25: New York City | G25: New York | H25: finance.yahoo.com | I25: Google Ad Manager | J25: Smartphone | K25: 286998 | L25: 815 | M25: 61586 | N25: 247500 | O25: 13 | P25: 6395.5506
A26: Automotive | B26: Auto Buyers | C26: Peugeot | D26: 300x250 | E26: Sign up Today - 10% Off | F26: New York City | G26: New York | H26: usatoday.com | I26: Google Ad Manager | J26: Smartphone | K26: 186404 | L26: 940 | M26: 30885 | N26: 151358 | O26: 3 | P26: 4702.0275
... A34: Automotive | B34: Auto Buyers | C34: Van | D34: 320x50 | E34: Sign up Today - 10% Off | F34: Chicago | G34: Illinois | H34: tasteofhome.com | I34: Google Ad Manager | J34: Smartphone | K34: 9153 | L34: 23 | M34: 4345 | N34: 8376 | O34: 14 | P34: 5007.5258
A35: Automotive | B35: Auto Buyers | D35: 320x50 | E35: Sign up Now - 10% Off | F35: Los Angeles | G35: California | H35: whatismyipaddress.com | I35: Google Ad Manager | J35: Smartphone | K35: 42830 | L35: 160 | M35: 24499 | N35: 34496 | O35: 5 | P35: 6261.5757
A36: Automotive | B36: Auto Buyers | C36: Crossover | D36: 320x50 | E36: Sign up Now - 10% Off | F36: Chicago | G36: Illinois | H36: usatoday.com | I36: Google Ad Manager | J36: Smartphone | K36: 25539 | L36: 78 | M36: 12130 | N36: 24129 | O36: 15 | P36: 4804.4932
A37: Automotive | B37: Auto Buyers | C37: Luxury | D37: 320x50 | E37: Sign up Now - 10% Off | F37: Los Angeles | G37: California | H37: al.com | I37: PubMatic | J37: Smartphone | K37: 14489 | L37: 37 | M37: 12453 | N37: 13873 | O37: 10 | P37: 6195.8407
A38: Automotive | B38: Auto Buyers | C38: SUV | D38: 300x250 | E38: Sign up Today - 10% Off | F38: New York City | G38: New York | H38: homeaddict.io | I38: BidSwitch | J38: Windows PC | K38: 99205 | L38: 230 | M38: 49240 | N38: 72687 | O38: 21 | P38: 6185.0025
A39: Automotive | B39: Auto Buyers | C39: Sedan | D39: 300x250 | E39: Sign up Today - 10% Off | F39: Chicago | G39: Illinois | H39: mail.aol.com | I39: Index Exchange | J39: Windows PC | K39: 25889 | L39: 110 | M39: 18382 | N39: 23328 | O39: 15 | P39: 4977.7848
A40: Automotive | B40: Auto Buyers | C40: Truck | D40: 300x250 | E40: Sign up Now - 10% Off | F40: Tampa-St Petersburg (Sarasota) | G40: Florida | H40: msn.com | I40: BidSwitch | J40: Smartphone | K40: 12974 | L40: 84 | M40: 7521 | N40: 10959 | O40: 7 | P40: 6301.8688
A41: Automotive | B41: Auto Car Purchase Next Year | C41: Yes | D41: 320x50 | E41: Subscribe Today - 10% Discount | F41: Grand Rapids-Kalamazoo | G41: Michigan | H41: whatismyipaddress.com | I41: Index Exchange | J41: Smartphone | K41: 31359 | L41: 66 | M41: 18348 | N41: 25950 | O41: 24 | P41: 1623.6148
A42: Automotive | B42: Auto Loyalists and Defectors | C42: Auto Make Defectors | D42: 320x50 | E42: Subscribe Today - 10% Discount | F42: Los Angeles | G42: California | H42: si.com | I42: TripleLift | J42: Smartphone | K42: 11561 | L42: 87 | M42: 4063 | N42: 9941 | O42: 5 | P42: 1911.932
A43: Automotive | B43: Boats and Watercraft | D43: 320x50 | E43: Subscribe Today - 10% Discount | F43: Chicago | G43: Illinois | H43: fandomwire.com | I43: OpenX | J43: Smartphone | K43: 111624 | L43: 590 | M43: 40343 | N43: 101306 | O43: 21 | P43: 6510.4467
A44: Automotive | B44: Brands | C44: Acura | D44: 300x250 | E44: Subscribe Today - 10% Discount | F44: New York City | G44: New York | H44: mail.aol.com | I44: Google Ad Manager | J44: Windows PC | K44: 83854 | L44: 197 | M44: 60626 | N44: 76071 | O44: 15 | P44: 5783.8438
A45: Automotive | B45: Brands | C45: Aston Martin | D45: 300x250 | E45: Subscribe Today - 10% Discount | F45: Orlando-Daytona Beach | G45: Florida | H45: yahoo.com | I45: Google Ad Manager | J45: Windows PC | K45: 84460 | L45: 209 | M45: 13169 | N45: 26688 | O45: 1 | P45: 4279.231
A46: Automotive | B46: Brands | C46: BMW | D46: 300x50 | E46: Sign up Now - 10% Off | F46: West Palm Beach-Ft. Pierce | G46: Florida | H46: forbes.com | I46: TripleLift | J46: Smartphone | K46: 88022 | L46: 370 | M46: 45972 | N46: 83922 | O46: 11 | P46: 5669.1448
A47: Automotive | B47: Brands | C47: Bugatti | D47: 320x50 | E47: Sign up Today - 10% Off | F47: Jacksonville | G47: Florida | H47: mobileposse.com | I47: Google Ad Manager | J47: Smartphone | K47: 98509 | L47: 299 | M47: 30688 | N47: 109518 | O47: 15 | P47: 2059.2703
A48: Automotive | B48: Brands | C48: Buick | D48: 300x250 | E48: Subscribe Today - 10% Discount | F48: South Bend-Elkhart | G48: Indiana | H48: signupgenius.com | I48: Google Ad Manager | J48: Apple PC | K48: 21599 | L48: 66 | M48: 13600 | N48: 20256 | O48: 9 | P48: 5551.3874
A49: Automotive | B49: Brands | C49: Cadillac | D49: 320x50 | E49: Subscribe Today - 10% Discount | F49: South Bend-Elkhart | G49: Indiana | H49: eenadu.net | I49: Google Ad Manager | J49: Smartphone | K49: 14011 | L49: 40 | M49: 5060 | N49: 12459 | O49: 5 | P49: 5632.088
A50: Automotive | B50: Brands | C50: Citroen | D50: 320x50 | E50: Sign up Today - 10% Off | F50: Little Rock-Pine Bluff | G50: Arkansas | H50: reuters.com | I50: Magnite DV+ | J50: Smartphone | K50: 9319 | L50: 30 | M50: 6193 | N50: 8682 | O50: 12 | P50: 4594.604
A51: Automotive | B51: Brands | C51: Dodge | D51: 300x250 | E51: 10% Discount - Ends 6/1 | F51: West Palm Beach-Ft. Pierce | G51: Florida | H51: autotrader.com | I51: BidSwitch | J51: Smartphone | K51: 43057 | L51: 122 | M51: 23767 | N51: 41484 | O51: 7 | P51: 5884.9314
A52: Automotive | B52: Brands | C52: Ferrari | D52: 300x250 | E52: Sign up Today - 10% Off | F52: Miami-Ft. Lauderdale | G52: Florida | H52: biblegateway.com | I52: Google Ad Manager | J52: Windows PC | K52: 88293 | L52: 255 | M52: 24101 | N52: 75557 | O52: 19 | P52: 5054.4816
A53: Automotive | B53: Brands | C53: Fiat | D53: 300x250 | E53: 10% Discount - Ends 6/1 | F53: Chicago | G53: Illinois | H53: thekrazycouponlady.com | I53: Magnite DV+ | J53: Smartphone | K53: 11417 | L53: 78 | M53: 1387 | N53: 9924 | O53: 9 | P53: 6206.6371
A54: Automotive | B54: Brands | C54: Ford | D54: 300x50 | E54: Sign up Today - 10% Off | F54: New York City | G54: New York | H54: insider.com | I54: Google Ad Manager | J54: Smartphone | K54: 89744 | L54: 311 | M54: 48786 | N54: 85900 | O54: 3 | P54: 6369.8112
A55: Automotive | B55: Brands | C55: GM-Daewoo | D55: 320x50 | E55: Sign up Now - 10% Off | F55: Rockford | G55: Illinois | H55: msn.com | I55: Google Ad Manager | J55: Smartphone | K55: 48436 | L55: 171 | M55: 16543 | N55: 42427 | O55: 6 | P55: 4386.6482
... A80: Automotive | B80: Decision Maker for Auto Purchase | C80: I was the sole decision-maker | D80: 300x250 | E80: Subscribe Today - 10% Discount | F80: New York City | G80: New York | H80: yahoo.com | I80: Google Ad Manager | J80: Smartphone | K80: 1116343 | L80: 3104 | M80: 550519 | N80: 977978 | O80: 9 | P80: 2494.2176
A81: Automotive | B81: Electric and Plug-In Vehicles | D81: 320x50 | E81: 10% Discount - Ends 6/1 | F81: San Francisco | G81: California | H81: msn.com | I81: PubMatic | J81: Smartphone | K81: 1601933 | L81: 4265 | M81: 1135085 | N81: 1487426 | O81: 29 | P81: 6785.7098
A82: Automotive | B82: Financial Intent | C82: Banking | D82: 300x50 | E82: Subscribe Today - 10% Discount | F82: San Francisco | G82: California | H82: mydailymagazine.com | I82: Google Ad Manager | J82: Smartphone | K82: 9238 | L82: 84 | M82: 4626 | N82: 8264 | O82: 15 | P82: 6683.2255
A83: Automotive | B83: Financial Intent | C83: Auto | D83: 320x50 | E83: Sign up Today - 10% Off | F83: Tallahassee | G83: Florida | H83: weather.com | I83: PubMatic | J83: Smartphone | K83: 42884 | L83: 104 | M83: 4345 | N83: 25153 | O83: 9 | P83: 6322.1527
A84: Automotive | B84: Financial Intent | C84: Loans and Credit | D84: 320x50 | E84: Sign up Now - 10% Off | F84: Savannah | G84: Georgia | H84: ebay.com | I84: Yieldmo | J84: Smartphone | K84: 83957 | L84: 185 | M84: 1420 | N84: 69246 | O84: 19 | P84: 6651.5145
A85: Automotive | B85: Hybrid and Alternative Vehicles | D85: 300x50 | E85: Sign up Now - 10% Off | F85: New York City | G85: New York | H85: hindustantimes.com | I85: Google Ad Manager | J85: Smartphone | K85: 17518 | L85: 60 | M85: 11513 | N85: 16192 | O85: 12 | P85: 6765.0004
A86: Automotive | B86: Primary Vehicle | C86: New | D86: 300x250 | E86: Sign up Today - 10% Off | F86: Los Angeles | G86: California | H86: dinneratthezoo.com | I86: Google Ad Manager | J86: Smartphone | K86: 12391 | L86: 40 | M86: 5756 | N86: 11636 | O86: 4 | P86: 3069.1235
A87: Automotive | B87: Primary Vehicle | C87: Pre-owned | D87: 320x50 | E87: Subscribe Today - 10% Discount | F87: Miami-Ft. Lauderdale | G87: Florida | H87: billboard.com | I87: Google Ad Manager | J87: Smartphone | K87: 11325 | L87: 88 | M87: 6186 | N87: 10612 | O87: 2 | P87: 1573.2541
A88: Automotive | B88: Primary Vehicle | C88: Company Car | D88: 320x50 | E88: 10% Discount - Ends 6/1 | F88: Hattiesburg-Laurel | G88: Mississippi | H88: onechicagocenter.com | I88: Magnite DV+ | J88: Smartphone | K88: 19829 | L88: 42 | M88: 15071 | N88: 19095 | O88: 2 | P88: 1952.4638
A89: Automotive | B89: Repair & Oil Change | C89: Intend | D89: 320x50 | E89: Subscribe Today - 10% Discount | F89: San Francisco | G89: California | H89: therighthairstyles.com | I89: Index Exchange | J89: Smartphone | K89: 9157 | L89: 60 | M89: 4520 | N89: 8037 | O89: 2 | P89: 1449.1778
A90: Automotive | B90: Services | C90: Arts and Entertainment | D90: 300x250 | E90: Sign up Today - 10% Off | F90: Chicago | G90: Illinois | H90: msn.com | I90: Google Ad Manager | J90: Apple PC | K90: 29834 | L90: 99 | M90: 14599 | N90: 24656 | O90: 14 | P90: 6032.8371
A91: Automotive | B91: Services | C91: Pets | D91: 300x250 | E91: Sign up Now - 10% Off | F91: Memphis | G91: Tennessee | H91: yahoo.com | I91: Magnite DV+ | J91: Smartphone | K91: 818919 | L91: 1987 | M91: 395852 | N91: 699064 | O91: 22 | P91: 6012.1025
A92: Automotive | B92: Services | C92: Photography | D92: 300x50 | E92: 10% Discount - Ends 6/1 | F92: Chicago | G92: Illinois | H92: mail.aol.com | I92: Google Ad Manager | J92: Smartphone | K92: 100058 | L92: 435 | M92: 73422 | N92: 91976 | O92: 8 | P92: 5831.2258
A93: Automotive | B93: Services | C93: Restaurants | D93: 300x250 | E93: Sign up Now - 10% Off | F93: San Francisco | G93: California | H93: weather.com | I93: Google Ad Manager | J93: Apple PC | K93: 29856 | L93: 111 | M93: 7664 | N93: 21698 | O93: 9 | P93: 4851.3944
A94: Automotive | B94: Shopping | C94: Auto Parts Stores | D94: 320x50 | E94: Subscribe Today - 10% Discount | F94: West Palm Beach-Ft. Pierce | G94: Florida | H94: insider.com | I94: Google Ad Manager | J94: Smartphone | K94: 102905 | L94: 421 | M94: 45324 | N94: 99065 | O94: 1 | P94: 6407.5818
A95: Automotive | B95: Shopping | C95: CPGï¿½ Cosmetics | D95: 320x50 | E95: Subscribe Today - 10% Discount | F95: Chicago | G95: Illinois | H95: weather.com | I95: Google Ad Manager | J95: Smartphone | K95: 43327 | L95: 140 | M95: 4689 | N95: 31363 | O95: 14 | P95: 4554.8769
A96: Automotive | B96: Shopping | C96: CPGï¿½ Grocery | D96: 300x250 | E96: Subscribe Today - 10% Discount | F96: New York City | G96: New York | H96: dailybee.com | I96: Google Ad Manager | J96: Smartphone | K96: 8111 | L96: 0 | M96: 4346 | N96: 6163 | O96: 1 | P96: 5000.7612
A97: Automotive | B97: Shopping | C97: CPGï¿½ Home Care | D97: 320x50 | E97: Subscribe Today - 10% Discount | F97: Tampa-St Petersburg (Sarasota) | G97: Florida | H97: weather.com | I97: Google Ad Manager | J97: Smartphone | K97: 210700 | L97: 704 | M97: 94625 | N97: 180681 | O97: 3 | P97: 6341.8793
... A124: Automotive | B124: Vehicle Ownership | C124: yes | D124: 300x50 | E124: Sign up Today - 10% Off | F124: Chicago | G124: Illinois | H124: mail.yahoo.com | I124: Google Ad Manager | J124: Smartphone | K124: 562103 | L124: 1450 | M124: 340616 | N124: 488921 | O124: 8 | P124: 1733.8302
A125: Automotive | B125: Vehicle Parts and Accessories | D125: 300x250 | E125: Subscribe Today - 10% Discount | F125: Miami-Ft. Lauderdale | G125: Florida | H125: pandora.com | I125: Xandr - Monetize SSP (AppNexus) | J125: Smartphone | K125: 58477 | L125: 135 | M125: 43554 | N125: 56558 | O125: 19 | P125: 5247.6239
A126: Automotive | B126: Vehicle Shopping | C126: Fuel Economy and Gas Prices | D126: 320x50 | E126: Sign up Today - 10% Off | F126: New York City | G126: New York | H126: nbcnews.com | I126: Google Ad Manager | J126: Smartphone | K126: 92764 | L126: 320 | M126: 19625 | N126: 76531 | O126: 14 | P126: 6730.0125
A127: B2B | B127: Decision Maker Responsibilities | C127: Accounting or Tax Services | D127: 320x50 | E127: Sign up Today - 10% Off | F127: Miami-Ft. Lauderdale | G127: Florida | H127: doodle.com | I127: Google Ad Manager | J127: Smartphone | K127: 12606 | L127: 74 | M127: 8332 | N127: 11170 | O127: 5 | P127: 2002.538
A128: B2B | B128: Decision Maker Responsibilities | C128: Advertising Services | D128: 320x50 | E128: Sign up Now - 10% Off | F128: Grand Rapids-Kalamazoo | G128: Michigan | H128: dmv.org | I128: BidSwitch | J128: Smartphone | K128: 14917 | L128: 10 | M128: 3065 | N128: 13109 | O128: 3 | P128: 1583.5371
A129: B2B | B129: Decision Maker Responsibilities | C129: Company Liability or Insurance | D129: 300x250 | E129: 10% Discount - Ends 6/1 | F129: Miami-Ft. Lauderdale | G129: Florida | H129: citationmachine.net | I129: Google Ad Manager | J129: Windows PC | K129: 31443 | L129: 70 | M129: 19134 | N129: 28059 | O129: 9 | P129: 2122.7659
A130: B2B | B130: Decision Maker Responsibilities | C130: Computer Hardware | D130: 320x50 | E130: 10% Discount - Ends 6/1 | F130: San Francisco | G130: California | H130: finance.yahoo.com | I130: Sovrn | J130: Smartphone | K130: 51056 | L130: 120 | M130: 24672 | N130: 45563 | O130: 4 | P130: 2215.6318
A131: B2B | B131: Decision Maker Responsibilities | C131: Computer Software | D131: 300x250 | E131: Subscribe Today - 10% Discount | F131: Los Angeles | G131: California | H131: mail.aol.com | I131: BidSwitch | J131: Smartphone | K131: 136733 | L131: 110 | M131: 102728 | N131: 127130 | O131: 4 | P131: 1946.0504
A132: B2B | B132: Decision Maker Responsibilities | C132: Employee Benefits | D132: 320x50 | E132: Subscribe Today - 10% Discount | F132: Jacksonville | G132: Florida | H132: classmates.com | I132: Magnite DV+ | J132: Smartphone | K132: 12451 | L132: 30 | M132: 2987 | N132: 11295 | O132: 4 | P132: 2127.3238
A133: B2B | B133: Decision Maker Responsibilities | C133: Financial Services | D133: 300x250 | E133: Sign up Now - 10% Off | F133: New York City | G133: New York | H133: androidpolice.com | I133: Taboola | J133: Apple PC | K133: 11668 | L133: 110 | M133: 7860 | N133: 11009 | O133: 5 | P133: 2653.9816
A134: B2B | B134: Decision Maker Responsibilities | C134: HR or Personnel Services | D134: 300x250 | E134: Sign up Today - 10% Off | F134: Los Angeles | G134: California | H134: foxnews.com | I134: Google Ad Manager | J134: Windows PC | K134: 51889 | L134: 174 | M134: 33879 | N134: 49382 | O134: 5 | P134: 2172.8417
A135: B2B | B135: Decision Maker Responsibilities | C135: Internet Services | D135: 300x250 | E135: Sign up Today - 10% Off | F135: Los Angeles | G135: California | H135: people.com | I135: Google Ad Manager | J135: Windows PC | K135: 31625 | L135: 99 | M135: 23764 | N135: 29364 | O135: 6 | P135: 2360.5552
A136: B2B | B136: Decision Maker Responsibilities | C136: Marketing or Market Research | D136: 320x50 | E136: Sign up Now - 10% Off | F136: Jacksonville | G136: Florida | H136: fortune.com | I136: Google Ad Manager | J136: Smartphone | K136: 54134 | L136: 155 | M136: 37418 | N136: 51299 | O136: 4 | P136: 1502.0178
A137: B2B | B137: Decision Maker Responsibilities | C137: Office Services or Moving | D137: 300x250 | E137: Sign up Today - 10% Off | F137: Nashville | G137: Tennessee | H137: realtor.com | I137: BidSwitch | J137: Apple PC | K137: 49412 | L137: 170 | M137: 22155 | N137: 43802 | O137: 3 | P137: 1595.6595
... A161: B2B | B161: Purchase DM | C161: Hardware and or Software I make the final decision with input from staff | D161: 300x250 | E161: 10% Discount - Ends 6/1 | F161: West Palm Beach-Ft. Pierce | G161: Florida | H161: taboolanews.com | I161: TripleLift | J161: Smartphone | K161: 217824 | L161: 560 | M161: 75089 | N161: 179723 | O161: 16 | P161: 1451.8085
A162: Beauty and Fitness | B162: Beauty Pageants | D162: 300x250 | E162: Sign up Today - 10% Off | F162: Chicago | G162: Illinois | H162: yahoo.com | I162: BidSwitch | J162: Apple PC | K162: 7584 | L162: 40 | M162: 3093 | N162: 6897 | O162: 2 | P162: 4467.0808
A163: Beauty and Fitness | B163: Body Art | D163: 320x50 | E163: 10% Discount - Ends 6/1 | F163: Nashville | G163: Tennessee | H163: finance.yahoo.com | I163: Google Ad Manager | J163: Smartphone | K163: 22690 | L163: 68 | M163: 10212 | N163: 19934 | O163: 19 | P163: 7210.6865
A164: Beauty and Fitness | B164: Cosmetology and Beauty Professionals | D164: 320x50 | E164: Subscribe Today - 10% Discount | F164: New York City | G164: New York | H164: dotesports.com | I164: Xandr - Monetize SSP (AppNexus) | J164: Smartphone | K164: 18022 | L164: 30 | M164: 10618 | N164: 16643 | O164: 15 | P164: 4051.1587
A165: Beauty and Fitness | B165: Face and Body Care | C165: Hygiene and Toiletries | D165: 300x250 | E165: Sign up Now - 10% Off | F165: Chicago | G165: Illinois | H165: the-sun.com | I165: OpenX | J165: Smartphone | K165: 247106 | L165: 750 | M165: 159618 | N165: 233150 | O165: 32 | P165: 7629.9443
A166: Beauty and Fitness | B166: Face and Body Care | C166: Make-Up and Cosmetics | D166: 300x250 | E166: 10% Discount - Ends 6/1 | F166: San Francisco | G166: California | H166: zdnet.com | I166: BidSwitch | J166: Apple PC | K166: 7585 | L166: 13 | M166: 5396 | N166: 7417 | O166: 24 | P166: 7082.6538
A167: Beauty and Fitness | B167: Face and Body Care | C167: Skin and Nail Care | D167: 300x50 | E167: 10% Discount - Ends 6/1 | F167: Los Angeles | G167: California | H167: apnews.com | I167: BidSwitch | J167: Smartphone | K167: 100800 | L167: 185 | M167: 14473 | N167: 85424 | O167: 10 | P167: 7004.7305
A168: Beauty and Fitness | B168: Face and Body Care | C168: Unwanted Body and Facial Hair Removal | D168: 300x250 | E168: Subscribe Today - 10% Discount | F168: New York City | G168: New York | H168: cnn.com | I168: Google Ad Manager | J168: Smartphone | K168: 106392 | L168: 299 | M168: 39599 | N168: 94941 | O168: 3 | P168: 6542.6124
A169: Beauty and Fitness | B169: Fashion and Style | D169: 320x50 | E169: 10% Discount - Ends 6/1 | F169: Miami-Ft. Lauderdale | G169: Florida | H169: miamiherald.com | I169: Xandr - Monetize SSP (AppNexus) | J169: Smartphone | K169: 7320 | L169: 33 | M169: 4020 | N169: 6692 | O169: 15 | P169: 1730.3736
A170: Beauty and Fitness | B170: Fashion and Style | C170: Fashion Designers and Collections | D170: 300x250 | E170: Sign up Now - 10% Off | F170: Miami-Ft. Lauderdale | G170: Florida | H170: mail.yahoo.com | I170: Google Ad Manager | J170: Smartphone | K170: 23774 | L170: 60 | M170: 10735 | N170: 21076 | O170: 24 | P170: 7657.108
A171: Beauty and Fitness | B171: Fashion and Style | C171: Fashion Modeling | D171: 320x50 | E171: Sign up Now - 10% Off | F171: Chicago | G171: Illinois | H171: forbes.com | I171: Google Ad Manager | J171: Smartphone | K171: 18095 | L171: 50 | M171: 10021 | N171: 16755 | O171: 24 | P171: 6768.7588
A172: Beauty and Fitness | B172: Fitness | D172: 300x250 | E172: 10% Discount - Ends 6/1 | F172: Chicago | G172: Illinois | H172: mail.yahoo.com | I172: BidSwitch | J172: Smartphone | K172: 728841 | L172: 2174 | M172: 424340 | N172: 634059 | O172: 37 | P172: 8054.1414
A173: Beauty and Fitness | B173: Fitness | C173: Bodybuilding | D173: 300x250 | E173: 10% Discount - Ends 6/1 | F173: West Palm Beach-Ft. Pierce | G173: Florida | H173: pandora.com | I173: Magnite DV+ | J173: Smartphone | K173: 57168 | L173: 160 | M173: 43261 | N173: 55261 | O173: 12 | P173: 5841.1514
A174: Beauty and Fitness | B174: Fitness | C174: Fitness Equipment and Accessories | D174: 300x250 | E174: Sign up Now - 10% Off | F174: Tampa-St Petersburg (Sarasota) | G174: Florida | H174: travelerdreams.com | I174: Google Ad Manager | J174: Windows PC | K174: 24875 | L174: 67 | M174: 14213 | N174: 23455 | O174: 8 | P174: 4652.2421
A175: Beauty and Fitness | B175: Fitness | C175: Fitness Instruction and Personal Training | D175: 300x250 | E175: Sign up Now - 10% Off | F175: Chicago | G175: Illinois | H175: accuweather.com | I175: Magnite DV+ | J175: Apple PC | K175: 23156 | L175: 73 | M175: 4468 | N175: 18821 | O175: 15 | P175: 6173.4129
A176: Beauty and Fitness | B176: Fitness | C176: Gyms and Health Clubs | D176: 320x50 | E176: Sign up Today - 10% Off | F176: New York City | G176: New York | H176: rollingstone.com | I176: Google Ad Manager | J176: Smartphone | K176: 25835 | L176: 69 | M176: 3753 | N176: 20808 | O176: 11 | P176: 5751.9123
A177: Beauty and Fitness | B177: Fitness | C177: Home Exercise | D177: 300x250 | E177: 10% Discount - Ends 6/1 | F177: Orlando-Daytona Beach | G177: Florida | H177: nbcnews.com | I177: Yahoo Exchange | J177: Smartphone | K177: 14224 | L177: 30 | M177: 2549 | N177: 11974 | O177: 7 | P177: 5637.3035
A178: Beauty and Fitness | B178: Fitness | C178: Yoga and Pilates | D178: 300x250 | E178: 10% Discount - Ends 6/1 | F178: New York City | G178: New York | H178: fandomwire.com | I178: PubMatic | J178: Windows PC | K178: 95644 | L178: 240 | M178: 13294 | N178: 86775 | O178: 9 | P178: 5587.7637
A179: Beauty and Fitness | B179: Hair Care | D179: 320x50 | E179: Sign up Today - 10% Off | F179: San Francisco | G179: California | H179: msn.com | I179: Google Ad Manager | J179: Smartphone | K179: 999915 | L179: 2748 | M179: 618816 | N179: 829942 | O179: 23 | P179: 7879.3168
A180: Beauty and Fitness | B180: Spas and Beauty Services | D180: 320x50 | E180: Sign up Today - 10% Off | F180: Chicago | G180: Illinois | H180: yahoo.com | I180: PubMatic | J180: Smartphone | K180: 888037 | L180: 2841 | M180: 370429 | N180: 820340 | O180: 42 | P180: 8134.3505
...
